Workbook
Name Slicer_City__Location: #N/A
Name Slicer_Industry_Vertical: #N/A
Name Slicer_Year1: #N/A

Sheet Total funding by IndustryVertic
A3: Row Labels | B3: Sum of Amount in USD
A4: Ecommerce | B4: 7163710608
A5: Consumer Internet | B5: 6245504245
A6: Transportation | B6: 3916632394
A7: Technology | B7: 2228607930
A8: Finance | B8: 1960938000
A9: nan | B9: 1230961368
A10: FinTech | B10: 1224211265
A11: E-commerce | B11: 1077793109
A12: Online Marketplace | B12: 700143000
A13: E-Commerce & M-Commerce platform | B13: 680000000
A14: B2B | B14: 587000000
A15: Car Aggregator & Retail Mobile App | B15: 500000000
... A797: Grand Total | B797: 37783048854

Sheet Top 10 Investors by amount
A3: Row Labels | B3: Sum of Amount in USD
A4: Westbridge Capital | B4: 3952000000
A5: Softbank | B5: 2500000000
A6: SoftBank Group | B6: 1467000000
A7: Microsoft, eBay, Tencent Holdings | B7: 1400000000
A8: Vijay Shekhar Sharma | B8: 1000150000
A9: Steadview Capital and existing investors | B9: 700000000
A10: Alibaba Group, Ant Financial | B10: 680000000
A11: N/A | B11: 615605951
A12: SoftBank Vision Fund | B12: 601000000
A13: Altimeter Capital, DST Global | B13: 585000000
A14: Baillie Gifford, Falcon Edge Capital, Tiger Global, SoftBank Group, DST Global, Didi Kuaidi | B14: 500000000
A15: Alibaba, Foxconn, Softbank | B15: 500000000
... A2375: Grand Total | B2375: 37783048854

Sheet Group Funding Amount
A3: Row Labels | B3: Sum of Amount in USD
A4: Bin1 | B4: 249922145
A5: Bin2 | B5: 3256168084
A6: Bin3 | B6: 34276958625
A7: Grand Total | B7: 37783048854

Sheet Funding by Year
A3: Row Labels | B3: Sum of Amount in USD
A4: 2015 | B4: 8556207368
A5: 2016 | B5: 3828058608
A6: 2017 | B6: 10429309730
A7: 2018 | B7: 5107818369
A8: 2019 | B8: 9471447525
A9: 2020 | B9: 390207254
A10: Grand Total | B10: 37783048854

Sheet Lookup 4
A3: Row Labels | B3: Sum of Amount in USD
A4: Angel | B4: 1752767523
A5: VC | B5: 8485526729
A6: Grand Total | B6: 10238294252

Sheet Average funding by industry
A3: Row Labels | B3: Average of Amount in USD
A4: Transportation | B4: 9.791581e+08
A5: E-Commerce & M-Commerce platform | B5: 680000000
A6: Ecommerce Marketplace | B6: 500000000
A7: Car Aggregator & Retail Mobile App | B7: 500000000
A8: Cab Aggregator | B8: 400000000
A9: Online Marketplace | B9: 350071500
A10: Automation | B10: 300000000
A11: B2B | B11: 293500000
A12: B2B Platform | B12: 225000000
A13: E-Tech | B13: 200000000
A14: Online Classifieds | B14: 150000000
A15: Last Mile Transportation | B15: 141650000
... A797: Grand Total | B797: 12542838

Sheet Total Funding
A3: Sum of Amount in USD
A4: 37854283854

Sheet Top Investor
A3: Row Labels | B3: Sum of Amount in USD
A4: Westbridge Capital | B4: 3952000000
A5: Grand Total | B5: 3952000000

Sheet Top City
A3: Row Labels | B3: Sum of Amount in USD
A4: Bangalore | B4: 8389991108
A5: Grand Total | B5: 8389991108

Sheet DashBoard
AL1: ="Indian Startup Funding Trends (" & TEXT(MIN(AC26:AC31), "0") & "–" & TEXT(MAX(AC26:AC31), "0") & ")" -> Indian Startup Funding Trends (2015–2020)
AC9: Sum of Amount in USD
AC10: 37854283854
AC12: Row Labels | AD12: Sum of Amount in USD
AC13: Westbridge Capital | AD13: 3952000000
AC14: Grand Total | AD14: 3952000000
AC17: Row Labels | AD17: Sum of Amount in USD
AC18: Bangalore | AD18: 8389991108
AC19: Grand Total | AD19: 8389991108
AC25: Year
AC26: 2015
AC27: 2016
AC28: 2017
AC29: 2018
AC30: 2019
AC31: 2020

Sheet Industry Share
A3: Row Labels | B3: Count of Industry Vertical
A4: Consumer Internet | B4: 938
A5: Technology | B5: 478
A6: Ecommerce | B6: 258
A7: nan | B7: 169
A8: Healthcare | B8: 71
A9: Finance | B9: 61
A10: E-commerce | B10: 40
A11: Logistics | B11: 32
A12: Education | B12: 23
A13: Food & Beverage | B13: 23
A14: Ed-Tech | B14: 15
A15: FinTech | B15: 10
... A797: Grand Total | B797: 3024

Sheet Funding Trend
A3: Row Labels | B3: Sum of Amount in USD
A4: 2017 | B4: 10429309730
A5: 2019 | B5: 9471447525
A6: 2015 | B6: 8627442368
A7: 2018 | B7: 5107818369
A8: 2016 | B8: 3828058608
A9: 2020 | B9: 390207254
A10: Grand Total | B10: 37854283854

Sheet Dynamic title
D2: ="Indian Startup Funding Trends (" & A4 & ")" -> Indian Startup Funding Trends (2015)
A3: Row Labels
A4: 2015
A5: 2016
A6: 2017
A7: 2018
A8: 2019
A9: 2020
A10: Grand Total

Sheet startup_funding
A1: Sr No | B1: Date dd/mm/yyyy | C1: Startup Name | D1: Industry Vertical | E1: SubVertical | F1: City Location | G1: Investors Name | H1: InvestmentnType | I1: Amount in USD | J1: Remarks | K1: Bins | L1: Year | M1: City(Xlookup) | N1: Investor Type | O1: Classification Investor Type | T1: Scroll Right to See table | W1: Investors Name | X1: InvestmentnType
A2: 1 | B2: 43839 | C2: BYJU’S | D2: E-Tech | E2: E-learning | F2: Bengaluru | G2: Tiger Global Management | H2: Private Equity Round | I2: 200000000 | K2: {=_xlfn.IFS(I2<1000000,"Bin1",AND(I2>=1000000,I2<=10000000),"Bin2",I2>10000000,"Bin3")} -> Bin3 | L2: =YEAR(B2) -> 2020 | M2: =_xlfn.XLOOKUP(C2,'LookUp Table'!$A$1:$A$3031,'LookUp Table'!$B$1:$B$3031,"Not Found",0) -> Bengaluru | N2: =IFERROR(VLOOKUP(G2,$W$1:$X$6025,2,FALSE),"Ignore") -> Private Equity Round | O2: =_xlfn.XLOOKUP(N2,'Com LookUp+Pivot'!$A$1:$A$49,'Com LookUp+Pivot'!$B$1:$B$49,"Not Found",0) -> PE | W2: Tiger Global Management | X2: Private Equity Round
A3: 2 | B3: 43843 | C3: Shuttl | D3: Transportation | E3: App based shuttle service | F3: Gurgaon | G3: Susquehanna Growth Equity | H3: Series C | I3: 8048394 | K3: {=_xlfn.IFS(I3<1000000,"Bin1",AND(I3>=1000000,I3<=10000000),"Bin2",I3>10000000,"Bin3")} -> Bin2 | L3: =YEAR(B3) -> 2020 | M3: =_xlfn.XLOOKUP(C3,'LookUp Table'!$A$1:$A$3031,'LookUp Table'!$B$1:$B$3031,"Not Found",0) -> Gurgaon | N3: =IFERROR(VLOOKUP(G3,$W$1:$X$6025,2,FALSE),"Ignore") -> Series C | O3: =_xlfn.XLOOKUP(N3,'Com LookUp+Pivot'!$A$1:$A$49,'Com LookUp+Pivot'!$B$1:$B$49,"Not Found",0) -> VC | W3: Susquehanna Growth Equity | X3: Series C
A4: 3 | B4: 43839 | C4: Mamaearth | D4: E-commerce | E4: Retailer of baby and toddler products | F4: Bengaluru | G4: Sequoia Capital India | H4: Series B | I4: 18358860 | K4: {=_xlfn.IFS(I4<1000000,"Bin1",AND(I4>=1000000,I4<=10000000),"Bin2",I4>10000000,"Bin3")} -> Bin3 | L4: =YEAR(B4) -> 2020 | M4: =_xlfn.XLOOKUP(C4,'LookUp Table'!$A$1:$A$3031,'LookUp Table'!$B$1:$B$3031,"Not Found",0) -> Bengaluru | N4: =IFERROR(VLOOKUP(G4,$W$1:$X$6025,2,FALSE),"Ignore") -> Series B | O4: =_xlfn.XLOOKUP(N4,'Com LookUp+Pivot'!$A$1:$A$49,'Com LookUp+Pivot'!$B$1:$B$49,"Not Found",0) -> VC | W4: Sequoia Capital India | X4: Series B
A5: 4 | B5: 43832 | C5: https://www.wealthbucket.in/ | D5: FinTech | E5: Online Investment | F5: New Delhi | G5: Vinod Khatumal | H5: Pre-series A | I5: 3000000 | K5: {=_xlfn.IFS(I5<1000000,"Bin1",AND(I5>=1000000,I5<=10000000),"Bin2",I5>10000000,"Bin3")} -> Bin2 | L5: =YEAR(B5) -> 2020 | M5: =_xlfn.XLOOKUP(C5,'LookUp Table'!$A$1:$A$3031,'LookUp Table'!$B$1:$B$3031,"Not Found",0) -> New Delhi | N5: =IFERROR(VLOOKUP(G5,$W$1:$X$6025,2,FALSE),"Ignore") -> Pre-series A | O5: =_xlfn.XLOOKUP(N5,'Com LookUp+Pivot'!$A$1:$A$49,'Com LookUp+Pivot'!$B$1:$B$49,"Not Found",0) -> VC | W5: Vinod Khatumal | X5: Pre-series A
A6: 5 | B6: 43832 | C6: Fashor | D6: Fashion and Apparel | E6: Embroiled Clothes For Women | F6: Mumbai | G6: Sprout Venture Partners | H6: Seed Round | I6: 1800000 | K6: {=_xlfn.IFS(I6<1000000,"Bin1",AND(I6>=1000000,I6<=10000000),"Bin2",I6>10000000,"Bin3")} -> Bin2 | L6: =YEAR(B6) -> 2020 | M6: =_xlfn.XLOOKUP(C6,'LookUp Table'!$A$1:$A$3031,'LookUp Table'!$B$1:$B$3031,"Not Found",0) -> Mumbai | N6: =IFERROR(VLOOKUP(G6,$W$1:$X$6025,2,FALSE),"Ignore") -> Seed Round | O6: =_xlfn.XLOOKUP(N6,'Com LookUp+Pivot'!$A$1:$A$49,'Com LookUp+Pivot'!$B$1:$B$49,"Not Found",0) -> Angel | W6: Sprout Venture Partners | X6: Seed Round
A7: 6 | B7: 43843 | C7: Pando | D7: Logistics | E7: Open-market, freight management platform | F7: Chennai | G7: Chiratae Ventures | H7: Series A | I7: 9000000 | K7: {=_xlfn.IFS(I7<1000000,"Bin1",AND(I7>=1000000,I7<=10000000),"Bin2",I7>10000000,"Bin3")} -> Bin2 | L7: =YEAR(B7) -> 2020 | M7: =_xlfn.XLOOKUP(C7,'LookUp Table'!$A$1:$A$3031,'LookUp Table'!$B$1:$B$3031,"Not Found",0) -> Chennai | N7: =IFERROR(VLOOKUP(G7,$W$1:$X$6025,2,FALSE),"Ignore") -> Series A | O7: =_xlfn.XLOOKUP(N7,'Com LookUp+Pivot'!$A$1:$A$49,'Com LookUp+Pivot'!$B$1:$B$49,"Not Found",0) -> VC | W7: Chiratae Ventures | X7: Series A
A8: 7 | B8: 43840 | C8: Zomato | D8: Hospitality | E8: Online Food Delivery Platform | F8: Gurgaon | G8: Ant Financial | H8: Private Equity Round | I8: 150000000 | K8: {=_xlfn.IFS(I8<1000000,"Bin1",AND(I8>=1000000,I8<=10000000),"Bin2",I8>10000000,"Bin3")} -> Bin3 | L8: =YEAR(B8) -> 2020 | M8: =_xlfn.XLOOKUP(C8,'LookUp Table'!$A$1:$A$3031,'LookUp Table'!$B$1:$B$3031,"Not Found",0) -> Gurgaon | N8: =IFERROR(VLOOKUP(G8,$W$1:$X$6025,2,FALSE),"Ignore") -> Private Equity Round | O8: =_xlfn.XLOOKUP(N8,'Com LookUp+Pivot'!$A$1:$A$49,'Com LookUp+Pivot'!$B$1:$B$49,"Not Found",0) -> PE | W8: Ant Financial | X8: Private Equity Round
A9: 8 | B9: 43811 | C9: Ecozen | D9: Technology | E9: Agritech | F9: Pune | G9: Sathguru Catalyzer Advisors | H9: Series A | I9: 6000000 | K9: {=_xlfn.IFS(I9<1000000,"Bin1",AND(I9>=1000000,I9<=10000000),"Bin2",I9>10000000,"Bin3")} -> Bin2 | L9: =YEAR(B9) -> 2019 | M9: =_xlfn.XLOOKUP(C9,'LookUp Table'!$A$1:$A$3031,'LookUp Table'!$B$1:$B$3031,"Not Found",0) -> Pune | N9: =IFERROR(VLOOKUP(G9,$W$1:$X$6025,2,FALSE),"Ignore") -> Series A | O9: =_xlfn.XLOOKUP(N9,'Com LookUp+Pivot'!$A$1:$A$49,'Com LookUp+Pivot'!$B$1:$B$49,"Not Found",0) -> VC | W9: Sathguru Catalyzer Advisors | X9: Series A
A10: 9 | B10: 43805 | C10: CarDekho | D10: E-Commerce | E10: Automobile | F10: Gurgaon | G10: Ping An Global Voyager Fund | H10: Series D | I10: 70000000 | K10: {=_xlfn.IFS(I10<1000000,"Bin1",AND(I10>=1000000,I10<=10000000),"Bin2",I10>10000000,"Bin3")} -> Bin3 | L10: =YEAR(B10) -> 2019 | M10: =_xlfn.XLOOKUP(C10,'LookUp Table'!$A$1:$A$3031,'LookUp Table'!$B$1:$B$3031,"Not Found",0) -> Gurgaon | N10: =IFERROR(VLOOKUP(G10,$W$1:$X$6025,2,FALSE),"Ignore") -> Series D | O10: =_xlfn.XLOOKUP(N10,'Com LookUp+Pivot'!$A$1:$A$49,'Com LookUp+Pivot'!$B$1:$B$49,"Not Found",0) -> VC | W10: Ping An Global Voyager Fund | X10: Series D
A11: 10 | B11: 43802 | C11: Dhruva Space | D11: Aerospace | E11: Satellite Communication | F11: Bengaluru | G11: Mumbai Angels, Ravikanth Reddy | H11: Seed | I11: 50000000 | K11: {=_xlfn.IFS(I11<1000000,"Bin1",AND(I11>=1000000,I11<=10000000),"Bin2",I11>10000000,"Bin3")} -> Bin3 | L11: =YEAR(B11) -> 2019 | M11: =_xlfn.XLOOKUP(C11,'LookUp Table'!$A$1:$A$3031,'LookUp Table'!$B$1:$B$3031,"Not Found",0) -> Bengaluru | N11: =IFERROR(VLOOKUP(G11,$W$1:$X$6025,2,FALSE),"Ignore") -> Seed | O11: =_xlfn.XLOOKUP(N11,'Com LookUp+Pivot'!$A$1:$A$49,'Com LookUp+Pivot'!$B$1:$B$49,"Not Found",0) -> Angel | W11: Mumbai Angels, Ravikanth Reddy | X11: Seed
A12: 11 | B12: 43812 | C12: Rivigo | D12: Technology | E12: Logistics Services and Solutions | F12: Gurgaon | G12: SAIF Partners, Spring Canter Investment Ltd. | H12: Series F | I12: 20000000 | K12: {=_xlfn.IFS(I12<1000000,"Bin1",AND(I12>=1000000,I12<=10000000),"Bin2",I12>10000000,"Bin3")} -> Bin3 | L12: =YEAR(B12) -> 2019 | M12: =_xlfn.XLOOKUP(C12,'LookUp Table'!$A$1:$A$3031,'LookUp Table'!$B$1:$B$3031,"Not Found",0) -> Gurgaon | N12: =IFERROR(VLOOKUP(G12,$W$1:$X$6025,2,FALSE),"Ignore") -> Series F | O12: =_xlfn.XLOOKUP(N12,'Com LookUp+Pivot'!$A$1:$A$49,'Com LookUp+Pivot'!$B$1:$B$49,"Not Found",0) -> VC | W12: SAIF Partners, Spring Canter Investment Ltd. | X12: Series F
A13: 12 | B13: 43816 | C13: Healthians | D13: B2B-focused foodtech startup | E13: Food Solutions For Corporate | F13: Bengaluru | G13: Paytm, NPTK, Sabre Partners and Neoplux | H13: Series C | I13: 12000000 | K13: {=_xlfn.IFS(I13<1000000,"Bin1",AND(I13>=1000000,I13<=10000000),"Bin2",I13>10000000,"Bin3")} -> Bin3 | L13: =YEAR(B13) -> 2019 | M13: =_xlfn.XLOOKUP(C13,'LookUp Table'!$A$1:$A$3031,'LookUp Table'!$B$1:$B$3031,"Not Found",0) -> Bengaluru | N13: =IFERROR(VLOOKUP(G13,$W$1:$X$6025,2,FALSE),"Ignore") -> Series C | O13: =_xlfn.XLOOKUP(N13,'Com LookUp+Pivot'!$A$1:$A$49,'Com LookUp+Pivot'!$B$1:$B$49,"Not Found",0) -> VC | W13: Paytm, NPTK, Sabre Partners and Neoplux | X13: Series C
... A43: 44 | B43: 43711 | C43: Vyapar App | D43: Accounting | E43: Mobile-based Accounting Software | F43: Bengaluru | G43: India Quotient, Axilor Ventures | H43: Series A | I43: 5000000 | K43: {=_xlfn.IFS(I43<1000000,"Bin1",AND(I43>=1000000,I43<=10000000),"Bin2",I43>10000000,"Bin3")} -> Bin2 | L43: =YEAR(B43) -> 2019 | M43: =_xlfn.XLOOKUP(C43,'LookUp Table'!$A$1:$A$3031,'LookUp Table'!$B$1:$B$3031,"Not Found",0) -> Bengaluru | N43: =IFERROR(VLOOKUP(G43,$W$1:$X$6025,2,FALSE),"Ignore") -> Series A | O43: =_xlfn.XLOOKUP(N43,'Com LookUp+Pivot'!$A$1:$A$49,'Com LookUp+Pivot'!$B$1:$B$49,"Not Found",0) -> VC | W43: India Quotient, Axilor Ventures | X43: Series A
A44: 45 | B44: 43678 | C44: CarDekho | D44: E-Commerce | E44: Automotive | F44: Gurgaon | G44: SC GG India Mobility Holdings LLC | H44: Series C | I44: 20000000 | J44: nan | K44: {=_xlfn.IFS(I44<1000000,"Bin1",AND(I44>=1000000,I44<=10000000),"Bin2",I44>10000000,"Bin3")} -> Bin3 | L44: =YEAR(B44) -> 2019 | M44: =_xlfn.XLOOKUP(C44,'LookUp Table'!$A$1:$A$3031,'LookUp Table'!$B$1:$B$3031,"Not Found",0) -> Gurgaon | N44: =IFERROR(VLOOKUP(G44,$W$1:$X$6025,2,FALSE),"Ignore") -> Series C | O44: =_xlfn.XLOOKUP(N44,'Com LookUp+Pivot'!$A$1:$A$49,'Com LookUp+Pivot'!$B$1:$B$49,"Not Found",0) -> VC | W44: SC GG India Mobility Holdings LLC | X44: Series C
A45: 46 | B45: 43678 | C45: Progcap | D45: Finance | E45: Supply Chain Management | F45: New Delhi | G45: Sequoia India | H45: Series A | I45: 5000000 | J45: nan | K45: {=_xlfn.IFS(I45<1000000,"Bin1",AND(I45>=1000000,I45<=10000000),"Bin2",I45>10000000,"Bin3")} -> Bin2 | L45: =YEAR(B45) -> 2019 | M45: =_xlfn.XLOOKUP(C45,'LookUp Table'!$A$1:$A$3031,'LookUp Table'!$B$1:$B$3031,"Not Found",0) -> New Delhi | N45: =IFERROR(VLOOKUP(G45,$W$1:$X$6025,2,FALSE),"Ignore") -> Series A | O45: =_xlfn.XLOOKUP(N45,'Com LookUp+Pivot'!$A$1:$A$49,'Com LookUp+Pivot'!$B$1:$B$49,"Not Found",0) -> VC | W45: Sequoia India | X45: Series A
A46: 48 | B46: 43678 | C46: Alteria Capital | D46: Finance | E46: VC Funds | F46: Mumbai | G46: Azim Premji, Binny Bansal | H46: Single Venture | I46: 140000000 | J46: nan | K46: {=_xlfn.IFS(I46<1000000,"Bin1",AND(I46>=1000000,I46<=10000000),"Bin2",I46>10000000,"Bin3")} -> Bin3 | L46: =YEAR(B46) -> 2019 | M46: =_xlfn.XLOOKUP(C46,'LookUp Table'!$A$1:$A$3031,'LookUp Table'!$B$1:$B$3031,"Not Found",0) -> Mumbai | N46: =IFERROR(VLOOKUP(G46,$W$1:$X$6025,2,FALSE),"Ignore") -> Single Venture | O46: =_xlfn.XLOOKUP(N46,'Com LookUp+Pivot'!$A$1:$A$49,'Com LookUp+Pivot'!$B$1:$B$49,"Not Found",0) -> Other | W46: Azim Premji, Binny Bansal | X46: Single Venture
A47: 49 | B47: 43678 | C47: Pine Labs | D47: Information Technology | E47: Last-mile retail transaction technology | F47: Noida | G47: Pine Labs Pte Ltd | H47: Corporate Round | I47: 38080000 | J47: nan | K47: {=_xlfn.IFS(I47<1000000,"Bin1",AND(I47>=1000000,I47<=10000000),"Bin2",I47>10000000,"Bin3")} -> Bin3 | L47: =YEAR(B47) -> 2019 | M47: =_xlfn.XLOOKUP(C47,'LookUp Table'!$A$1:$A$3031,'LookUp Table'!$B$1:$B$3031,"Not Found",0) -> Noida | N47: =IFERROR(VLOOKUP(G47,$W$1:$X$6025,2,FALSE),"Ignore") -> Corporate Round | O47: =_xlfn.XLOOKUP(N47,'Com LookUp+Pivot'!$A$1:$A$49,'Com LookUp+Pivot'!$B$1:$B$49,"Not Found",0) -> Other | W47: Pine Labs Pte Ltd | X47: Corporate Round
A48: 50 | B48: 43689 | C48: Meesho | D48: E-Commerce | E48: Social Commerce | F48: Bengaluru | G48: Naspers | H48: Series D | I48: 125000000 | J48: nan | K48: {=_xlfn.IFS(I48<1000000,"Bin1",AND(I48>=1000000,I48<=10000000),"Bin2",I48>10000000,"Bin3")} -> Bin3 | L48: =YEAR(B48) -> 2019 | M48: =_xlfn.XLOOKUP(C48,'LookUp Table'!$A$1:$A$3031,'LookUp Table'!$B$1:$B$3031,"Not Found",0) -> Bengaluru | N48: =IFERROR(VLOOKUP(G48,$W$1:$X$6025,2,FALSE),"Ignore") -> Series D | O48: =_xlfn.XLOOKUP(N48,'Com LookUp+Pivot'!$A$1:$A$49,'Com LookUp+Pivot'!$B$1:$B$49,"Not Found",0) -> VC | W48: Naspers | X48: Series D
A49: 51 | B49: 43690 | C49: Cars24 | D49: E-Commerce | E49: Car Retail | F49: Gurugram | G49: MS Dhoni | H49: Series D | I49: 11000000 | J49: nan | K49: {=_xlfn.IFS(I49<1000000,"Bin1",AND(I49>=1000000,I49<=10000000),"Bin2",I49>10000000,"Bin3")} -> Bin3 | L49: =YEAR(B49) -> 2019 | M49: =_xlfn.XLOOKUP(C49,'LookUp Table'!$A$1:$A$3031,'LookUp Table'!$B$1:$B$3031,"Not Found",0) -> Gurugram | N49: =IFERROR(VLOOKUP(G49,$W$1:$X$6025,2,FALSE),"Ignore") -> Series D | O49: =_xlfn.XLOOKUP(N49,'Com LookUp+Pivot'!$A$1:$A$49,'Com LookUp+Pivot'!$B$1:$B$49,"Not Found",0) -> VC | W49: MS Dhoni | X49: Series D
A50: 52 | B50: 43690 | C50: Uniphore | D50: Customer Service Platform | E50: Conversational AI | F50: Palo Alto | G50: March Capital Partners | H50: Series C | I50: 51000000 | J50: nan | K50: {=_xlfn.IFS(I50<1000000,"Bin1",AND(I50>=1000000,I50<=10000000),"Bin2",I50>10000000,"Bin3")} -> Bin3 | L50: =YEAR(B50) -> 2019 | M50: =_xlfn.XLOOKUP(C50,'LookUp Table'!$A$1:$A$3031,'LookUp Table'!$B$1:$B$3031,"Not Found",0) -> Palo Alto | N50: =IFERROR(VLOOKUP(G50,$W$1:$X$6025,2,FALSE),"Ignore") -> Series C | O50: =_xlfn.XLOOKUP(N50,'Com LookUp+Pivot'!$A$1:$A$49,'Com LookUp+Pivot'!$B$1:$B$49,"Not Found",0) -> VC | W50: March Capital Partners | X50: Series C
A51: 53 | B51: 43700 | C51: Zendrive | D51: Automotive | E51: Road Safety Analytics | F51: San Francisco | G51: XL Innovate | H51: Series B | I51: 37000000 | J51: nan | K51: {=_xlfn.IFS(I51<1000000,"Bin1",AND(I51>=1000000,I51<=10000000),"Bin2",I51>10000000,"Bin3")} -> Bin3 | L51: =YEAR(B51) -> 2019 | M51: =_xlfn.XLOOKUP(C51,'LookUp Table'!$A$1:$A$3031,'LookUp Table'!$B$1:$B$3031,"Not Found",0) -> San Francisco | N51: =IFERROR(VLOOKUP(G51,$W$1:$X$6025,2,FALSE),"Ignore") -> Series B | O51: =_xlfn.XLOOKUP(N51,'Com LookUp+Pivot'!$A$1:$A$49,'Com LookUp+Pivot'!$B$1:$B$49,"Not Found",0) -> VC | W51: XL Innovate | X51: Series B
A52: 54 | B52: 43700 | C52: Lo! Foods | D52: Consumer Goods | E52: Low carb food for Diabetics | F52: Bengaluru | G52: Rashmi Daga (founder, FreshMenu), Raveen Sastry (co-founder, Myntra) and Mitesh Shah (finance chief, BookMyShow) | H52: Seed Round | I52: 500000 | J52: nan | K52: {=_xlfn.IFS(I52<1000000,"Bin1",AND(I52>=1000000,I52<=10000000),"Bin2",I52>10000000,"Bin3")} -> Bin1 | L52: =YEAR(B52) -> 2019 | M52: =_xlfn.XLOOKUP(C52,'LookUp Table'!$A$1:$A$3031,'LookUp Table'!$B$1:$B$3031,"Not Found",0) -> Bengaluru | N52: =IFERROR(VLOOKUP(G52,$W$1:$X$6025,2,FALSE),"Ignore") -> Seed Round | O52: =_xlfn.XLOOKUP(N52,'Com LookUp+Pivot'!$A$1:$A$49,'Com LookUp+Pivot'!$B$1:$B$49,"Not Found",0) -> Angel | W52: Rashmi Daga (founder, FreshMenu), Raveen Sastry (co-founder, Myntra) and Mitesh Shah (finance chief, BookMyShow) | X52: Seed Round
A53: 55 | B53: 43700 | C53: Tala | D53: FinTech | E53: Digital Lending Platform | F53: Santa Monica | G53: RPS Ventures | H53: Series D | I53: 110000000 | J53: nan | K53: {=_xlfn.IFS(I53<1000000,"Bin1",AND(I53>=1000000,I53<=10000000),"Bin2",I53>10000000,"Bin3")} -> Bin3 | L53: =YEAR(B53) -> 2019 | M53: =_xlfn.XLOOKUP(C53,'LookUp Table'!$A$1:$A$3031,'LookUp Table'!$B$1:$B$3031,"Not Found",0) -> Santa Monica | N53: =IFERROR(VLOOKUP(G53,$W$1:$X$6025,2,FALSE),"Ignore") -> Series D | O53: =_xlfn.XLOOKUP(N53,'Com LookUp+Pivot'!$A$1:$A$49,'Com LookUp+Pivot'!$B$1:$B$49,"Not Found",0) -> VC | W53: RPS Ventures | X53: Series D
A54: 56 | B54: 43699 | C54: INDwealth | D54: FinTech | E54: Wealth Management | F54: Gurgaon | G54: Tiger Global Management | H54: Venture Round | I54: 15000000 | J54: nan | K54: {=_xlfn.IFS(I54<1000000,"Bin1",AND(I54>=1000000,I54<=10000000),"Bin2",I54>10000000,"Bin3")} -> Bin3 | L54: =YEAR(B54) -> 2019 | M54: =_xlfn.XLOOKUP(C54,'LookUp Table'!$A$1:$A$3031,'LookUp Table'!$B$1:$B$3031,"Not Found",0) -> Gurgaon | N54: =IFERROR(VLOOKUP(G54,$W$1:$X$6025,2,FALSE),"Ignore") -> Private Equity Round | O54: =_xlfn.XLOOKUP(N54,'Com LookUp+Pivot'!$A$1:$A$49,'Com LookUp+Pivot'!$B$1:$B$49,"Not Found",0) -> PE | W54: Tiger Global Management | X54: Venture Round
A55: 57 | B55: 43698 | C55: HungerBox | D55: Food and Beverage | E55: B2B Foodtech | F55: Bengaluru | G55: One97 Communications Ltd. | H55: Series C | I55: 6590000 | J55: nan | K55: {=_xlfn.IFS(I55<1000000,"Bin1",AND(I55>=1000000,I55<=10000000),"Bin2",I55>10000000,"Bin3")} -> Bin2 | L55: =YEAR(B55) -> 2019 | M55: =_xlfn.XLOOKUP(C55,'LookUp Table'!$A$1:$A$3031,'LookUp Table'!$B$1:$B$3031,"Not Found",0) -> Bengaluru | N55: =IFERROR(VLOOKUP(G55,$W$1:$X$6025,2,FALSE),"Ignore") -> Series C | O55: =_xlfn.XLOOKUP(N55,'Com LookUp+Pivot'!$A$1:$A$49,'Com LookUp+Pivot'!$B$1:$B$49,"Not Found",0) -> VC | W55: One97 Communications Ltd. | X55: Series C
... A105: 109 | B105: 43574 | C105: My Healthcare | D105: E-commerce | E105: Software Solutions | F105: Bengaluru and Gurugram | G105: Sixth Sense Ventures | H105: Series A | I105: 3000000 | J105: nan | K105: {=_xlfn.IFS(I105<1000000,"Bin1",AND(I105>=1000000,I105<=10000000),"Bin2",I105>10000000,"Bin3")} -> Bin2 | L105: =YEAR(B105) -> 2019 | M105: =_xlfn.XLOOKUP(C105,'LookUp Table'!$A$1:$A$3031,'LookUp Table'!$B$1:$B$3031,"Not Found",0) -> Bengaluru and Gurugram | N105: =IFERROR(VLOOKUP(G105,$W$1:$X$6025,2,FALSE),"Ignore") -> Series B | O105: =_xlfn.XLOOKUP(N105,'Com LookUp+Pivot'!$A$1:$A$49,'Com LookUp+Pivot'!$B$1:$B$49,"Not Found",0) -> VC | W105: Sixth Sense Ventures | X105: Series A
A106: 110 | B106: 43574 | C106: KrazyBee | D106: E-commerce | E106: Lending Platform | F106: Bengaluru | G106: BAC Acquisitions, Unifi AIF, BRD Securities, Northern R Capital | H106: Debt | I106: 14,342,000+ | J106: nan | K106: {=_xlfn.IFS(I106<1000000,"Bin1",AND(I106>=1000000,I106<=10000000),"Bin2",I106>10000000,"Bin3")} -> Bin3 | L106: =YEAR(B106) -> 2019 | M106: =_xlfn.XLOOKUP(C106,'LookUp Table'!$A$1:$A$3031,'LookUp Table'!$B$1:$B$3031,"Not Found",0) -> Bengaluru | N106: =IFERROR(VLOOKUP(G106,$W$1:$X$6025,2,FALSE),"Ignore") -> Debt | O106: =_xlfn.XLOOKUP(N106,'Com LookUp+Pivot'!$A$1:$A$49,'Com LookUp+Pivot'!$B$1:$B$49,"Not Found",0) -> Other | W106: BAC Acquisitions, Unifi AIF, BRD Securities, Northern R Capital | X106: Debt
A107: 111 | B107: 43572 | C107: Shuttl | D107: Transportation | E107: Bus Aggregation | F107: Gurugram | G107: New Atlantic Ventures | H107: Venture Round | I107: 5000000 | J107: nan | K107: {=_xlfn.IFS(I107<1000000,"Bin1",AND(I107>=1000000,I107<=10000000),"Bin2",I107>10000000,"Bin3")} -> Bin2 | L107: =YEAR(B107) -> 2019 | M107: =_xlfn.XLOOKUP(C107,'LookUp Table'!$A$1:$A$3031,'LookUp Table'!$B$1:$B$3031,"Not Found",0) -> Gurgaon | N107: =IFERROR(VLOOKUP(G107,$W$1:$X$6025,2,FALSE),"Ignore") -> Venture Round | O107: =_xlfn.XLOOKUP(N107,'Com LookUp+Pivot'!$A$1:$A$49,'Com LookUp+Pivot'!$B$1:$B$49,"Not Found",0) -> Other | W107: New Atlantic Ventures | X107: Venture Round
A108: 112 | B108: 43572 | C108: Increff | D108: Technology | E108: Supply-chain technology solutions | F108: Bengaluru | G108: 021 Capita, Binny Bansal | H108: Series A | I108: 3000000 | J108: nan | K108: {=_xlfn.IFS(I108<1000000,"Bin1",AND(I108>=1000000,I108<=10000000),"Bin2",I108>10000000,"Bin3")} -> Bin2 | L108: =YEAR(B108) -> 2019 | M108: =_xlfn.XLOOKUP(C108,'LookUp Table'!$A$1:$A$3031,'LookUp Table'!$B$1:$B$3031,"Not Found",0) -> Bengaluru | N108: =IFERROR(VLOOKUP(G108,$W$1:$X$6025,2,FALSE),"Ignore") -> Series A | O108: =_xlfn.XLOOKUP(N108,'Com LookUp+Pivot'!$A$1:$A$49,'Com LookUp+Pivot'!$B$1:$B$49,"Not Found",0) -> VC | W108: 021 Capita, Binny Bansal | X108: Series A
A109: 113 | B109: 43497 | C109: FleetX | D109: AI | E109: Logistics | F109: Gurgaon | G109: India Quotient and LetsVenture\\xe2\\x80\\x99s Angel Fund | H109: Pre Series A | I109: 0 | J109: nan | K109: {=_xlfn.IFS(I109<1000000,"Bin1",AND(I109>=1000000,I109<=10000000),"Bin2",I109>10000000,"Bin3")} -> Bin1 | L109: =YEAR(B109) -> 2019 | M109: =_xlfn.XLOOKUP(C109,'LookUp Table'!$A$1:$A$3031,'LookUp Table'!$B$1:$B$3031,"Not Found",0) -> Gurgaon | N109: =IFERROR(VLOOKUP(G109,$W$1:$X$6025,2,FALSE),"Ignore") -> Pre Series A | O109: =_xlfn.XLOOKUP(N109,'Com LookUp+Pivot'!$A$1:$A$49,'Com LookUp+Pivot'!$B$1:$B$49,"Not Found",0) -> VC | W109: India Quotient and LetsVenture\\xe2\\x80\\x99s Angel Fund | X109: Pre Series A
A110: 114 | B110: 43504 | C110: Zilingo | D110: Ecommerce | E110: Fashion & Apparel | F110: India/Singapore | G110: Sequoia Capital and Temasek Holdings, EDBI, Burda Principal Investments, and Sofina | H110: Series D | I110: 226000000 | J110: nan | K110: {=_xlfn.IFS(I110<1000000,"Bin1",AND(I110>=1000000,I110<=10000000),"Bin2",I110>10000000,"Bin3")} -> Bin3 | L110: =YEAR(B110) -> 2019 | M110: =_xlfn.XLOOKUP(C110,'LookUp Table'!$A$1:$A$3031,'LookUp Table'!$B$1:$B$3031,"Not Found",0) -> India/Singapore | N110: =IFERROR(VLOOKUP(G110,$W$1:$X$6025,2,FALSE),"Ignore") -> Series D | O110: =_xlfn.XLOOKUP(N110,'Com LookUp+Pivot'!$A$1:$A$49,'Com LookUp+Pivot'!$B$1:$B$49,"Not Found",0) -> VC | W110: Sequoia Capital and Temasek Holdings, EDBI, Burda Principal Investments, and Sofina | X110: Series D
A111: 115 | B111: 43509 | C111: NanoClean Global | D111: Nanotechnology | E111: Anti-Pollution | F111: New Delhi | G111: LetsVenture, PitchRight Venture, 91SpringBoard, AL Nour International Holdings and Mark V Investments | H111: Series A | I111: 600000 | J111: nan | K111: {=_xlfn.IFS(I111<1000000,"Bin1",AND(I111>=1000000,I111<=10000000),"Bin2",I111>10000000,"Bin3")} -> Bin1 | L111: =YEAR(B111) -> 2019 | M111: =_xlfn.XLOOKUP(C111,'LookUp Table'!$A$1:$A$3031,'LookUp Table'!$B$1:$B$3031,"Not Found",0) -> New Delhi | N111: =IFERROR(VLOOKUP(G111,$W$1:$X$6025,2,FALSE),"Ignore") -> Series A | O111: =_xlfn.XLOOKUP(N111,'Com LookUp+Pivot'!$A$1:$A$49,'Com LookUp+Pivot'!$B$1:$B$49,"Not Found",0) -> VC | W111: LetsVenture, PitchRight Venture, 91SpringBoard, AL Nour International Holdings and Mark V Investments | X111: Series A
A112: 116 | B112: 43145 | C112: OyoRooms | D112: Hospitality | E112: Budget Rooms | F112: Gurgaon | G112: DiDi Chuxing | H112: Equity | I112: 100000000 | J112: nan | K112: {=_xlfn.IFS(I112<1000000,"Bin1",AND(I112>=1000000,I112<=10000000),"Bin2",I112>10000000,"Bin3")} -> Bin3 | L112: =YEAR(B112) -> 2018 | M112: =_xlfn.XLOOKUP(C112,'LookUp Table'!$A$1:$A$3031,'LookUp Table'!$B$1:$B$3031,"Not Found",0) -> Gurgaon | N112: =IFERROR(VLOOKUP(G112,$W$1:$X$6025,2,FALSE),"Ignore") -> Equity | O112: =_xlfn.XLOOKUP(N112,'Com LookUp+Pivot'!$A$1:$A$49,'Com LookUp+Pivot'!$B$1:$B$49,"Not Found",0) -> PE | W112: DiDi Chuxing | X112: Equity
A113: 117 | B113: 43468 | C113: CarDekho | D113: Automobile | E113: Online Marketplace | F113: Jaipur | G113: Sequoia India, Hillhouse Capital, Alphabet\\xe2\\x80\\x99s growth investment arm Capital G and Axis Bank | H113: Series C | I113: 110000000 | J113: nan | K113: {=_xlfn.IFS(I113<1000000,"Bin1",AND(I113>=1000000,I113<=10000000),"Bin2",I113>10000000,"Bin3")} -> Bin3 | L113: =YEAR(B113) -> 2019 | M113: =_xlfn.XLOOKUP(C113,'LookUp Table'!$A$1:$A$3031,'LookUp Table'!$B$1:$B$3031,"Not Found",0) -> Gurgaon | N113: =IFERROR(VLOOKUP(G113,$W$1:$X$6025,2,FALSE),"Ignore") -> Series C | O113: =_xlfn.XLOOKUP(N113,'Com LookUp+Pivot'!$A$1:$A$49,'Com LookUp+Pivot'!$B$1:$B$49,"Not Found",0) -> VC | W113: Sequoia India, Hillhouse Capital, Alphabet\\xe2\\x80\\x99s growth investment arm Capital G and Axis Bank | X113: Series C
A114: 118 | B114: 43469 | C114: Vyome Therapeutics Inc. | D114: Health and Wellness | E114: Specialty pharmaceutical | F114: India/US | G114: Iron Pillar, Perceptive Advisors, Romulus Capital and Kalaari Capital | H114: Series D | I114: 22000000 | J114: nan | K114: {=_xlfn.IFS(I114<1000000,"Bin1",AND(I114>=1000000,I114<=10000000),"Bin2",I114>10000000,"Bin3")} -> Bin3 | L114: =YEAR(B114) -> 2019 | M114: =_xlfn.XLOOKUP(C114,'LookUp Table'!$A$1:$A$3031,'LookUp Table'!$B$1:$B$3031,"Not Found",0) -> India/US | N114: =IFERROR(VLOOKUP(G114,$W$1:$X$6025,2,FALSE),"Ignore") -> Series D | O114: =_xlfn.XLOOKUP(N114,'Com LookUp+Pivot'!$A$1:$A$49,'Com LookUp+Pivot'!$B$1:$B$49,"Not Found",0) -> VC | W114: Iron Pillar, Perceptive Advisors, Romulus Capital and Kalaari Capital | X114: Series D
A115: 119 | B115: 43469 | C115: Samunnati Financial Intermediation & Services Pvt. Ltd | D115: Finance | E115: Non-banking financial company | F115: Chennai | G115: MASSIF, a Dutch government fund | H115: Debt-Funding | I115: 5000000 | J115: nan | K115: {=_xlfn.IFS(I115<1000000,"Bin1",AND(I115>=1000000,I115<=10000000),"Bin2",I115>10000000,"Bin3")} -> Bin2 | L115: =YEAR(B115) -> 2019 | M115: =_xlfn.XLOOKUP(C115,'LookUp Table'!$A$1:$A$3031,'LookUp Table'!$B$1:$B$3031,"Not Found",0) -> Chennai | N115: =IFERROR(VLOOKUP(G115,$W$1:$X$6025,2,FALSE),"Ignore") -> Debt-Funding | O115: =_xlfn.XLOOKUP(N115,'Com LookUp+Pivot'!$A$1:$A$49,'Com LookUp+Pivot'!$B$1:$B$49,"Not Found",0) -> Other | W115: MASSIF, a Dutch government fund | X115: Debt-Funding
A116: 120 | B116: 43438 | C116: Manch | D116: Social Media | E116: Hyperlocal Content | F116: Delhi | G116: Stellaris Venture Partners | H116: Seed Funding | I116: 700000 | J116: nan | K116: {=_xlfn.IFS(I116<1000000,"Bin1",AND(I116>=1000000,I116<=10000000),"Bin2",I116>10000000,"Bin3")} -> Bin1 | L116: =YEAR(B116) -> 2018 | M116: =_xlfn.XLOOKUP(C116,'LookUp Table'!$A$1:$A$3031,'LookUp Table'!$B$1:$B$3031,"Not Found",0) -> Delhi | N116: =IFERROR(VLOOKUP(G116,$W$1:$X$6025,2,FALSE),"Ignore") -> Seed Funding | O116: =_xlfn.XLOOKUP(N116,'Com LookUp+Pivot'!$A$1:$A$49,'Com LookUp+Pivot'!$B$1:$B$49,"Not Found",0) -> Angel | W116: Stellaris Venture Partners | X116: Seed Funding
A117: 121 | B117: 43435 | C117: UrbanClap Technologies Pvt. Ltd | D117: Services Platform | E117: Home services marketplace | F117: New Delhi | G117: Steadview Capital and Vy Capital. | H117: Series D | I117: 50000000 | J117: nan | K117: {=_xlfn.IFS(I117<1000000,"Bin1",AND(I117>=1000000,I117<=10000000),"Bin2",I117>10000000,"Bin3")} -> Bin3 | L117: =YEAR(B117) -> 2018 | M117: =_xlfn.XLOOKUP(C117,'LookUp Table'!$A$1:$A$3031,'LookUp Table'!$B$1:$B$3031,"Not Found",0) -> New Delhi | N117: =IFERROR(VLOOKUP(G117,$W$1:$X$6025,2,FALSE),"Ignore") -> Series D | O117: =_xlfn.XLOOKUP(N117,'Com LookUp+Pivot'!$A$1:$A$49,'Com LookUp+Pivot'!$B$1:$B$49,"Not Found",0) -> VC | W117: Steadview Capital and Vy Capital. | X117: Series D
A118: 122 | B118: 43436 | C118: Guiddoo | D118: Travel Tech | E118: Platform for travel agents | F118: Mumbai | G118: Individual Investors | H118: Pre-Series A | I118: 800000 | J118: nan | K118: {=_xlfn.IFS(I118<1000000,"Bin1",AND(I118>=1000000,I118<=10000000),"Bin2",I118>10000000,"Bin3")} -> Bin1 | L118: =YEAR(B118) -> 2018 | M118: =_xlfn.XLOOKUP(C118,'LookUp Table'!$A$1:$A$3031,'LookUp Table'!$B$1:$B$3031,"Not Found",0) -> Mumbai | N118: =IFERROR(VLOOKUP(G118,$W$1:$X$6025,2,FALSE),"Ignore") -> Pre-Series A | O118: =_xlfn.XLOOKUP(N118,'Com LookUp+Pivot'!$A$1:$A$49,'Com LookUp+Pivot'!$B$1:$B$49,"Not Found",0) -> VC | W118: Individual Investors | X118: Pre-Series A
... A232: 237 | B232: 43263 | C232: Daily Ninja | D232: Consumer Internet | E232: Hyperlocal Delivery Platform | F232: Bengaluru | G232: Saama Capital and Sequoia Capital | H232: Seed/ Angel Funding | I232: 3000000 | J232: nan | K232: {=_xlfn.IFS(I232<1000000,"Bin1",AND(I232>=1000000,I232<=10000000),"Bin2",I232>10000000,"Bin3")} -> Bin2 | L232: =YEAR(B232) -> 2018 | M232: =_xlfn.XLOOKUP(C232,'LookUp Table'!$A$1:$A$3031,'LookUp Table'!$B$1:$B$3031,"Not Found",0) -> Bengaluru | N232: =IFERROR(VLOOKUP(G232,$W$1:$X$6025,2,FALSE),"Ignore") -> Seed/ Angel Funding | O232: =_xlfn.XLOOKUP(N232,'Com LookUp+Pivot'!$A$1:$A$49,'Com LookUp+Pivot'!$B$1:$B$49,"Not Found",0) -> Angel | W232: Saama Capital and Sequoia Capital | X232: Seed/ Angel Funding
A233: 238 | B233: 43264 | C233: NirogStreet | D233: Healthcare | E233: An Online Platform That Connects Ayurveda Doctors With Patients | F233: Gurugram | G233: Spiral Ventures, Subho Ray and Samir Kumar | H233: Seed/ Angel Funding | I233: 3,000,00 | J233: nan | K233: {=_xlfn.IFS(I233<1000000,"Bin1",AND(I233>=1000000,I233<=10000000),"Bin2",I233>10000000,"Bin3")} -> Bin3 | L233: =YEAR(B233) -> 2018 | M233: =_xlfn.XLOOKUP(C233,'LookUp Table'!$A$1:$A$3031,'LookUp Table'!$B$1:$B$3031,"Not Found",0) -> Gurugram | N233: =IFERROR(VLOOKUP(G233,$W$1:$X$6025,2,FALSE),"Ignore") -> Seed/ Angel Funding | O233: =_xlfn.XLOOKUP(N233,'Com LookUp+Pivot'!$A$1:$A$49,'Com LookUp+Pivot'!$B$1:$B$49,"Not Found",0) -> Angel | W233: Spiral Ventures, Subho Ray and Samir Kumar | X233: Seed/ Angel Funding
A234: 239 | B234: 43264 | C234: Nivesh | D234: Finance | E234: Mass Market Mutual Fund Investment Platform | F234: Noida | G234: LetsVenture, Rajan Anandan, Basab Pradhan, Vivek Khare and Bijoy George | H234: Seed/ Angel Funding | I234: 450000 | J234: nan | K234: {=_xlfn.IFS(I234<1000000,"Bin1",AND(I234>=1000000,I234<=10000000),"Bin2",I234>10000000,"Bin3")} -> Bin1 | L234: =YEAR(B234) -> 2018 | M234: =_xlfn.XLOOKUP(C234,'LookUp Table'!$A$1:$A$3031,'LookUp Table'!$B$1:$B$3031,"Not Found",0) -> Noida | N234: =IFERROR(VLOOKUP(G234,$W$1:$X$6025,2,FALSE),"Ignore") -> Seed/ Angel Funding | O234: =_xlfn.XLOOKUP(N234,'Com LookUp+Pivot'!$A$1:$A$49,'Com LookUp+Pivot'!$B$1:$B$49,"Not Found",0) -> Angel | W234: LetsVenture, Rajan Anandan, Basab Pradhan, Vivek Khare and Bijoy George | X234: Seed/ Angel Funding
A235: 240 | B235: 43264 | C235: What\\xe2\\x80\\x99s Up Life | D235: Consumer Internet | E235: A Local Discovery App For Dining-Out, Party, Leisure and Events | F235: Gurugram | G235: Rannvijay Singha | H235: Seed/ Angel Funding | I235: 0 | J235: nan | K235: {=_xlfn.IFS(I235<1000000,"Bin1",AND(I235>=1000000,I235<=10000000),"Bin2",I235>10000000,"Bin3")} -> Bin1 | L235: =YEAR(B235) -> 2018 | M235: =_xlfn.XLOOKUP(C235,'LookUp Table'!$A$1:$A$3031,'LookUp Table'!$B$1:$B$3031,"Not Found",0) -> Gurugram | N235: =IFERROR(VLOOKUP(G235,$W$1:$X$6025,2,FALSE),"Ignore") -> Seed/ Angel Funding | O235: =_xlfn.XLOOKUP(N235,'Com LookUp+Pivot'!$A$1:$A$49,'Com LookUp+Pivot'!$B$1:$B$49,"Not Found",0) -> Angel | W235: Rannvijay Singha | X235: Seed/ Angel Funding
A236: 241 | B236: 43265 | C236: HomeLane | D236: Consumer Internet | E236: Online Home Furnishing Solutions | F236: Bengaluru | G236: Brand Capital | H236: Seed/ Angel Funding | I236: 3450000 | J236: nan | K236: {=_xlfn.IFS(I236<1000000,"Bin1",AND(I236>=1000000,I236<=10000000),"Bin2",I236>10000000,"Bin3")} -> Bin2 | L236: =YEAR(B236) -> 2018 | M236: =_xlfn.XLOOKUP(C236,'LookUp Table'!$A$1:$A$3031,'LookUp Table'!$B$1:$B$3031,"Not Found",0) -> Bengaluru | N236: =IFERROR(VLOOKUP(G236,$W$1:$X$6025,2,FALSE),"Ignore") -> Seed/ Angel Funding | O236: =_xlfn.XLOOKUP(N236,'Com LookUp+Pivot'!$A$1:$A$49,'Com LookUp+Pivot'!$B$1:$B$49,"Not Found",0) -> Angel | W236: Brand Capital | X236: Seed/ Angel Funding
A237: 242 | B237: 43265 | C237: Network Intelligence | D237: Technology | E237: Cybersecurity Specialist | F237: Mumbai | G237: Helix Investments | H237: Private Equity | I237: 4800000 | J237: nan | K237: {=_xlfn.IFS(I237<1000000,"Bin1",AND(I237>=1000000,I237<=10000000),"Bin2",I237>10000000,"Bin3")} -> Bin2 | L237: =YEAR(B237) -> 2018 | M237: =_xlfn.XLOOKUP(C237,'LookUp Table'!$A$1:$A$3031,'LookUp Table'!$B$1:$B$3031,"Not Found",0) -> Mumbai | N237: =IFERROR(VLOOKUP(G237,$W$1:$X$6025,2,FALSE),"Ignore") -> Private Equity | O237: =_xlfn.XLOOKUP(N237,'Com LookUp+Pivot'!$A$1:$A$49,'Com LookUp+Pivot'!$B$1:$B$49,"Not Found",0) -> PE | W237: Helix Investments | X237: Private Equity
A238: 243 | B238: 43269 | C238: Tynor Othontics | D238: Healthcare | E238: Prosthetics Manufacturers | F238: Chandigarh | G238: Lighthouse Funds & Thuasne Participations | H238: Private Equity | I238: 21000000 | J238: nan | K238: {=_xlfn.IFS(I238<1000000,"Bin1",AND(I238>=1000000,I238<=10000000),"Bin2",I238>10000000,"Bin3")} -> Bin3 | L238: =YEAR(B238) -> 2018 | M238: =_xlfn.XLOOKUP(C238,'LookUp Table'!$A$1:$A$3031,'LookUp Table'!$B$1:$B$3031,"Not Found",0) -> Chandigarh | N238: =IFERROR(VLOOKUP(G238,$W$1:$X$6025,2,FALSE),"Ignore") -> Private Equity | O238: =_xlfn.XLOOKUP(N238,'Com LookUp+Pivot'!$A$1:$A$49,'Com LookUp+Pivot'!$B$1:$B$49,"Not Found",0) -> PE | W238: Lighthouse Funds & Thuasne Participations | X238: Private Equity
A239: 244 | B239: 43269 | C239: Elucidata | D239: IT | E239: Data Analytics (SaaS) | F239: Delhi & Cambridge | G239: Hyperplane Venture Capital and several angel investors | H239: Seed/ Angel Funding | I239: 1700000 | J239: nan | K239: {=_xlfn.IFS(I239<1000000,"Bin1",AND(I239>=1000000,I239<=10000000),"Bin2",I239>10000000,"Bin3")} -> Bin2 | L239: =YEAR(B239) -> 2018 | M239: =_xlfn.XLOOKUP(C239,'LookUp Table'!$A$1:$A$3031,'LookUp Table'!$B$1:$B$3031,"Not Found",0) -> Delhi & Cambridge | N239: =IFERROR(VLOOKUP(G239,$W$1:$X$6025,2,FALSE),"Ignore") -> Seed/ Angel Funding | O239: =_xlfn.XLOOKUP(N239,'Com LookUp+Pivot'!$A$1:$A$49,'Com LookUp+Pivot'!$B$1:$B$49,"Not Found",0) -> Angel | W239: Hyperplane Venture Capital and several angel investors | X239: Seed/ Angel Funding
A240: 245 | B240: 43270 | C240: Chrysalis | D240: Ed-Tech | E240: Education Services Provider | F240: Pune | G240: Menterra Venture & Artha Initiatives | H240: Seed/ Angel Funding | I240: 0 | J240: nan | K240: {=_xlfn.IFS(I240<1000000,"Bin1",AND(I240>=1000000,I240<=10000000),"Bin2",I240>10000000,"Bin3")} -> Bin1 | L240: =YEAR(B240) -> 2018 | M240: =_xlfn.XLOOKUP(C240,'LookUp Table'!$A$1:$A$3031,'LookUp Table'!$B$1:$B$3031,"Not Found",0) -> Pune | N240: =IFERROR(VLOOKUP(G240,$W$1:$X$6025,2,FALSE),"Ignore") -> Seed/ Angel Funding | O240: =_xlfn.XLOOKUP(N240,'Com LookUp+Pivot'!$A$1:$A$49,'Com LookUp+Pivot'!$B$1:$B$49,"Not Found",0) -> Angel | W240: Menterra Venture & Artha Initiatives | X240: Seed/ Angel Funding
A241: 246 | B241: 43270 | C241: RentSher | D241: Consumer Internet | E241: Online Rental Marketplace | F241: Bengaluru | G241: Shorooq Investments, LetsVenture & Others | H241: Seed/ Angel Funding | I241: 1100000 | J241: nan | K241: {=_xlfn.IFS(I241<1000000,"Bin1",AND(I241>=1000000,I241<=10000000),"Bin2",I241>10000000,"Bin3")} -> Bin2 | L241: =YEAR(B241) -> 2018 | M241: =_xlfn.XLOOKUP(C241,'LookUp Table'!$A$1:$A$3031,'LookUp Table'!$B$1:$B$3031,"Not Found",0) -> Bengaluru | N241: =IFERROR(VLOOKUP(G241,$W$1:$X$6025,2,FALSE),"Ignore") -> Seed/ Angel Funding | O241: =_xlfn.XLOOKUP(N241,'Com LookUp+Pivot'!$A$1:$A$49,'Com LookUp+Pivot'!$B$1:$B$49,"Not Found",0) -> Angel | W241: Shorooq Investments, LetsVenture & Others | X241: Seed/ Angel Funding
A242: 247 | B242: 43271 | C242: Drip capital | D242: Finance | E242: Trade Finance Firm | F242: Mumbai | G242: Accel Partners, Sequoia India, Y Combinator and others. | H242: Private Equity | I242: 15000000 | J242: nan | K242: {=_xlfn.IFS(I242<1000000,"Bin1",AND(I242>=1000000,I242<=10000000),"Bin2",I242>10000000,"Bin3")} -> Bin3 | L242: =YEAR(B242) -> 2018 | M242: =_xlfn.XLOOKUP(C242,'LookUp Table'!$A$1:$A$3031,'LookUp Table'!$B$1:$B$3031,"Not Found",0) -> Mumbai | N242: =IFERROR(VLOOKUP(G242,$W$1:$X$6025,2,FALSE),"Ignore") -> Private Equity | O242: =_xlfn.XLOOKUP(N242,'Com LookUp+Pivot'!$A$1:$A$49,'Com LookUp+Pivot'!$B$1:$B$49,"Not Found",0) -> PE | W242: Accel Partners, Sequoia India, Y Combinator and others. | X242: Private Equity
A243: 248 | B243: 43273 | C243: WickedRide | D243: Consumer Internet | E243: Online Motorbike And Scooter Rental Platforms | F243: Bengaluru | G243: Sequoia Capital, Accel Partners & Raghunandan Gangappa | H243: Private Equity | I243: 9100000 | J243: nan | K243: {=_xlfn.IFS(I243<1000000,"Bin1",AND(I243>=1000000,I243<=10000000),"Bin2",I243>10000000,"Bin3")} -> Bin2 | L243: =YEAR(B243) -> 2018 | M243: =_xlfn.XLOOKUP(C243,'LookUp Table'!$A$1:$A$3031,'LookUp Table'!$B$1:$B$3031,"Not Found",0) -> Bengaluru | N243: =IFERROR(VLOOKUP(G243,$W$1:$X$6025,2,FALSE),"Ignore") -> Private Equity | O243: =_xlfn.XLOOKUP(N243,'Com LookUp+Pivot'!$A$1:$A$49,'Com LookUp+Pivot'!$B$1:$B$49,"Not Found",0) -> PE | W243: Sequoia Capital, Accel Partners & Raghunandan Gangappa | X243: Private Equity
A244: 249 | B244: 43276 | C244: PolicyBazaar | D244: Consumer Internet | E244: Online Insurance Selling Platform | F244: Gurugram | G244: SoftBank Vision Fund & Info Edge (India) Ltd | H244: Private Equity | I244: 200000000 | J244: nan | K244: {=_xlfn.IFS(I244<1000000,"Bin1",AND(I244>=1000000,I244<=10000000),"Bin2",I244>10000000,"Bin3")} -> Bin3 | L244: =YEAR(B244) -> 2018 | M244: =_xlfn.XLOOKUP(C244,'LookUp Table'!$A$1:$A$3031,'LookUp Table'!$B$1:$B$3031,"Not Found",0) -> Gurugram | N244: =IFERROR(VLOOKUP(G244,$W$1:$X$6025,2,FALSE),"Ignore") -> Private Equity | O244: =_xlfn.XLOOKUP(N244,'Com LookUp+Pivot'!$A$1:$A$49,'Com LookUp+Pivot'!$B$1:$B$49,"Not Found",0) -> PE | W244: SoftBank Vision Fund & Info Edge (India) Ltd | X244: Private Equity
A245: 250 | B245: 43276 | C245: HipBar | D245: Consumer Internet | E245: Digital Payment Platform For Beverage Delivery | F245: Bengaluru | G245: Diageo India | H245: Private Equity | I245: 4000000 | J245: nan | K245: {=_xlfn.IFS(I245<1000000,"Bin1",AND(I245>=1000000,I245<=10000000),"Bin2",I245>10000000,"Bin3")} -> Bin2 | L245: =YEAR(B245) -> 2018 | M245: =_xlfn.XLOOKUP(C245,'LookUp Table'!$A$1:$A$3031,'LookUp Table'!$B$1:$B$3031,"Not Found",0) -> Bengaluru | N245: =IFERROR(VLOOKUP(G245,$W$1:$X$6025,2,FALSE),"Ignore") -> Private Equity | O245: =_xlfn.XLOOKUP(N245,'Com LookUp+Pivot'!$A$1:$A$49,'Com LookUp+Pivot'!$B$1:$B$49,"Not Found",0) -> PE | W245: Diageo India | X245: Private Equity
... A274: 279 | B274: 43250 | C274: Stellaps | D274: Technology | E274: Iot Application Platform In Agriculture | F274: Bengaluru | G274: IndusAge Partners, Bill & Melinda Gates Foundation, Qualcomm Venture, ABB Technology Ventures, Omnivore, Blume Ventures, Venture Highway and BEENEXT | H274: Private Equity | I274: 14000000 | J274: nan | K274: {=_xlfn.IFS(I274<1000000,"Bin1",AND(I274>=1000000,I274<=10000000),"Bin2",I274>10000000,"Bin3")} -> Bin3 | L274: =YEAR(B274) -> 2018 | M274: =_xlfn.XLOOKUP(C274,'LookUp Table'!$A$1:$A$3031,'LookUp Table'!$B$1:$B$3031,"Not Found",0) -> Bengaluru | N274: =IFERROR(VLOOKUP(G274,$W$1:$X$6025,2,FALSE),"Ignore") -> Private Equity | O274: =_xlfn.XLOOKUP(N274,'Com LookUp+Pivot'!$A$1:$A$49,'Com LookUp+Pivot'!$B$1:$B$49,"Not Found",0) -> PE | W274: IndusAge Partners, Bill & Melinda Gates Foundation, Qualcomm Venture, ABB Technology Ventures, Omnivore, Blume Ventures, Venture Highway and BEENEXT | X274: Private Equity
A275: 280 | B275: 43251 | C275: Credright | D275: Consumer Internet | E275: Lending Platform For SMEs | F275: Hyderabad | G275: Accion Venture Lab, YourNest Venture Capital And Other Angel Investors | H275: Seed/ Angel Funding | I275: 13,000,00 | J275: nan | K275: {=_xlfn.IFS(I275<1000000,"Bin1",AND(I275>=1000000,I275<=10000000),"Bin2",I275>10000000,"Bin3")} -> Bin3 | L275: =YEAR(B275) -> 2018 | M275: =_xlfn.XLOOKUP(C275,'LookUp Table'!$A$1:$A$3031,'LookUp Table'!$B$1:$B$3031,"Not Found",0) -> Hyderabad | N275: =IFERROR(VLOOKUP(G275,$W$1:$X$6025,2,FALSE),"Ignore") -> Seed/ Angel Funding | O275: =_xlfn.XLOOKUP(N275,'Com LookUp+Pivot'!$A$1:$A$49,'Com LookUp+Pivot'!$B$1:$B$49,"Not Found",0) -> Angel | W275: Accion Venture Lab, YourNest Venture Capital And Other Angel Investors | X275: Seed/ Angel Funding
A276: 281 | B276: 43192 | C276: Fitternity | D276: Consumer Internet | E276: Online Fitness Discovey Platform | F276: Mumbai | G276: Exfinity Venture, Saha fund Partners, Arihant Patni of Patni Family Office, Anjali Bansal, Shardul Amarchand Mangaldas, Satish Khanna and Taparia family office. | H276: Private Equity | I276: 2000000 | J276: nan | K276: {=_xlfn.IFS(I276<1000000,"Bin1",AND(I276>=1000000,I276<=10000000),"Bin2",I276>10000000,"Bin3")} -> Bin2 | L276: =YEAR(B276) -> 2018 | M276: =_xlfn.XLOOKUP(C276,'LookUp Table'!$A$1:$A$3031,'LookUp Table'!$B$1:$B$3031,"Not Found",0) -> Mumbai | N276: =IFERROR(VLOOKUP(G276,$W$1:$X$6025,2,FALSE),"Ignore") -> Private Equity | O276: =_xlfn.XLOOKUP(N276,'Com LookUp+Pivot'!$A$1:$A$49,'Com LookUp+Pivot'!$B$1:$B$49,"Not Found",0) -> PE | W276: Exfinity Venture, Saha fund Partners, Arihant Patni of Patni Family Office, Anjali Bansal, Shardul Amarchand Mangaldas, Satish Khanna and Taparia family office. | X276: Private Equity
A277: 282 | B277: 43192 | C277: Synctag | D277: Technology | E277: Social Media Anlaytics Platform | F277: Coimbatore | G277: Subhkam Ventures and Mohit Khadaria | H277: Seed / Angel Funding | I277: 307600 | J277: nan | K277: {=_xlfn.IFS(I277<1000000,"Bin1",AND(I277>=1000000,I277<=10000000),"Bin2",I277>10000000,"Bin3")} -> Bin1 | L277: =YEAR(B277) -> 2018 | M277: =_xlfn.XLOOKUP(C277,'LookUp Table'!$A$1:$A$3031,'LookUp Table'!$B$1:$B$3031,"Not Found",0) -> Coimbatore | N277: =IFERROR(VLOOKUP(G277,$W$1:$X$6025,2,FALSE),"Ignore") -> Seed / Angel Funding | O277: =_xlfn.XLOOKUP(N277,'Com LookUp+Pivot'!$A$1:$A$49,'Com LookUp+Pivot'!$B$1:$B$49,"Not Found",0) -> Angel | W277: Subhkam Ventures and Mohit Khadaria | X277: Seed / Angel Funding
A278: 283 | B278: 43192 | C278: Benepik | D278: Technology | E278: Enhanced Employee Engagement Platform | F278: Gurugram | G278: Vishal Bali, Yogesh Misra, Thomas Assessments and others | H278: Seed / Angel Funding | I278: 0 | J278: nan | K278: {=_xlfn.IFS(I278<1000000,"Bin1",AND(I278>=1000000,I278<=10000000),"Bin2",I278>10000000,"Bin3")} -> Bin1 | L278: =YEAR(B278) -> 2018 | M278: =_xlfn.XLOOKUP(C278,'LookUp Table'!$A$1:$A$3031,'LookUp Table'!$B$1:$B$3031,"Not Found",0) -> Gurugram | N278: =IFERROR(VLOOKUP(G278,$W$1:$X$6025,2,FALSE),"Ignore") -> Seed / Angel Funding | O278: =_xlfn.XLOOKUP(N278,'Com LookUp+Pivot'!$A$1:$A$49,'Com LookUp+Pivot'!$B$1:$B$49,"Not Found",0) -> Angel | W278: Vishal Bali, Yogesh Misra, Thomas Assessments and others | X278: Seed / Angel Funding
A279: 284 | B279: 43192 | C279: Finzy | D279: Consumer Internet | E279: Online Loan Matchmaking Platform | F279: Bengaluru | G279: N/A | H279: Seed / Angel Funding | I279: 1300000 | J279: nan | K279: {=_xlfn.IFS(I279<1000000,"Bin1",AND(I279>=1000000,I279<=10000000),"Bin2",I279>10000000,"Bin3")} -> Bin2 | L279: =YEAR(B279) -> 2018 | M279: =_xlfn.XLOOKUP(C279,'LookUp Table'!$A$1:$A$3031,'LookUp Table'!$B$1:$B$3031,"Not Found",0) -> Bengaluru | N279: =IFERROR(VLOOKUP(G279,$W$1:$X$6025,2,FALSE),"Ignore") -> Seed / Angel Funding | O279: =_xlfn.XLOOKUP(N279,'Com LookUp+Pivot'!$A$1:$A$49,'Com LookUp+Pivot'!$B$1:$B$49,"Not Found",0) -> Angel | W279: N/A | X279: Seed / Angel Funding
A280: 285 | B280: 43194 | C280: Varthana | D280: Finance | E280: Loans and Services To Affordable Private Schools in India | F280: Bengaluru | G280: ChrysCapital, Existing investors, Elevar Equity, LGT Impact, Omidyar Network and Kaizen Private Equity also participated in the round | H280: Private Equity | I280: 55000000 | J280: nan | K280: {=_xlfn.IFS(I280<1000000,"Bin1",AND(I280>=1000000,I280<=10000000),"Bin2",I280>10000000,"Bin3")} -> Bin3 | L280: =YEAR(B280) -> 2018 | M280: =_xlfn.XLOOKUP(C280,'LookUp Table'!$A$1:$A$3031,'LookUp Table'!$B$1:$B$3031,"Not Found",0) -> Bengaluru | N280: =IFERROR(VLOOKUP(G280,$W$1:$X$6025,2,FALSE),"Ignore") -> Private Equity | O280: =_xlfn.XLOOKUP(N280,'Com LookUp+Pivot'!$A$1:$A$49,'Com LookUp+Pivot'!$B$1:$B$49,"Not Found",0) -> PE | W280: ChrysCapital, Existing investors, Elevar Equity, LGT Impact, Omidyar Network and Kaizen Private Equity also participated in the round | X280: Private Equity
A281: 286 | B281: 43195 | C281: IndigoLearn | D281: Ed-Tech | E281: Online Education Platform | F281: Hyderabad | G281: Maheshwar Peri, founder and chairman of career information portal Careers360, and Jamshed Jeejeebhoy, director at Byramjee Jeejeebhoy Pvt. Ltd were among the angels | H281: Seed / Angel Funding | I281: 150000 | J281: nan | K281: {=_xlfn.IFS(I281<1000000,"Bin1",AND(I281>=1000000,I281<=10000000),"Bin2",I281>10000000,"Bin3")} -> Bin1 | L281: =YEAR(B281) -> 2018 | M281: =_xlfn.XLOOKUP(C281,'LookUp Table'!$A$1:$A$3031,'LookUp Table'!$B$1:$B$3031,"Not Found",0) -> Hyderabad | N281: =IFERROR(VLOOKUP(G281,$W$1:$X$6025,2,FALSE),"Ignore") -> Seed / Angel Funding | O281: =_xlfn.XLOOKUP(N281,'Com LookUp+Pivot'!$A$1:$A$49,'Com LookUp+Pivot'!$B$1:$B$49,"Not Found",0) -> Angel | W281: Maheshwar Peri, founder and chairman of career information portal Careers360, and Jamshed Jeejeebhoy, director at Byramjee Jeejeebhoy Pvt. Ltd were among the angels | X281: Seed / Angel Funding
A282: 287 | B282: 43195 | C282: Vedantu | D282: Ed-Tech | E282: Interactive Online Tutoring Platform | F282: Bangalore | G282: Accel Partners, Tiger Global And Others | H282: Private Equity | I282: 10000000 | J282: nan | K282: {=_xlfn.IFS(I282<1000000,"Bin1",AND(I282>=1000000,I282<=10000000),"Bin2",I282>10000000,"Bin3")} -> Bin2 | L282: =YEAR(B282) -> 2018 | M282: =_xlfn.XLOOKUP(C282,'LookUp Table'!$A$1:$A$3031,'LookUp Table'!$B$1:$B$3031,"Not Found",0) -> Bangalore | N282: =IFERROR(VLOOKUP(G282,$W$1:$X$6025,2,FALSE),"Ignore") -> Private Equity | O282: =_xlfn.XLOOKUP(N282,'Com LookUp+Pivot'!$A$1:$A$49,'Com LookUp+Pivot'!$B$1:$B$49,"Not Found",0) -> PE | W282: Accel Partners, Tiger Global And Others | X282: Private Equity
A283: 288 | B283: 43199 | C283: Kaleidofin | D283: Fiinance | E283: Digital Financial Services Platform | F283: Chennai | G283: Omidyar Network. Blume Ventures and Professor Shlomo Ben-Haim | H283: Seed / Angel Funding | I283: 2800000 | J283: nan | K283: {=_xlfn.IFS(I283<1000000,"Bin1",AND(I283>=1000000,I283<=10000000),"Bin2",I283>10000000,"Bin3")} -> Bin2 | L283: =YEAR(B283) -> 2018 | M283: =_xlfn.XLOOKUP(C283,'LookUp Table'!$A$1:$A$3031,'LookUp Table'!$B$1:$B$3031,"Not Found",0) -> Chennai | N283: =IFERROR(VLOOKUP(G283,$W$1:$X$6025,2,FALSE),"Ignore") -> Seed / Angel Funding | O283: =_xlfn.XLOOKUP(N283,'Com LookUp+Pivot'!$A$1:$A$49,'Com LookUp+Pivot'!$B$1:$B$49,"Not Found",0) -> Angel | W283: Omidyar Network. Blume Ventures and Professor Shlomo Ben-Haim | X283: Seed / Angel Funding
A284: 289 | B284: 43199 | C284: Pipabella | D284: Consumer Internet | E284: Fashion Accessories Etailer | F284: Mumbai | G284: Fireside Ventures | H284: Seed / Angel Funding | I284: 1,000,000, | J284: nan | K284: {=_xlfn.IFS(I284<1000000,"Bin1",AND(I284>=1000000,I284<=10000000),"Bin2",I284>10000000,"Bin3")} -> Bin3 | L284: =YEAR(B284) -> 2018 | M284: =_xlfn.XLOOKUP(C284,'LookUp Table'!$A$1:$A$3031,'LookUp Table'!$B$1:$B$3031,"Not Found",0) -> Mumbai | N284: =IFERROR(VLOOKUP(G284,$W$1:$X$6025,2,FALSE),"Ignore") -> Seed / Angel Funding | O284: =_xlfn.XLOOKUP(N284,'Com LookUp+Pivot'!$A$1:$A$49,'Com LookUp+Pivot'!$B$1:$B$49,"Not Found",0) -> Angel | W284: Fireside Ventures | X284: Seed / Angel Funding
A285: 290 | B285: 43199 | C285: Elemential | D285: Technology | E285: Blockchain Platform | F285: Mumbai | G285: Matrix Partner, Amrish Rau, Investopad, Digital Currency Group, Hinduja Group, Lightspeed India, Eight Innovate, Amit Ranjan, Prashant Malik and others | H285: Seed / Angel Funding | I285: 0 | J285: nan | K285: {=_xlfn.IFS(I285<1000000,"Bin1",AND(I285>=1000000,I285<=10000000),"Bin2",I285>10000000,"Bin3")} -> Bin1 | L285: =YEAR(B285) -> 2018 | M285: =_xlfn.XLOOKUP(C285,'LookUp Table'!$A$1:$A$3031,'LookUp Table'!$B$1:$B$3031,"Not Found",0) -> Mumbai | N285: =IFERROR(VLOOKUP(G285,$W$1:$X$6025,2,FALSE),"Ignore") -> Seed / Angel Funding | O285: =_xlfn.XLOOKUP(N285,'Com LookUp+Pivot'!$A$1:$A$49,'Com LookUp+Pivot'!$B$1:$B$49,"Not Found",0) -> Angel | W285: Matrix Partner, Amrish Rau, Investopad, Digital Currency Group, Hinduja Group, Lightspeed India, Eight Innovate, Amit Ranjan, Prashant Malik and others | X285: Seed / Angel Funding
A286: 291 | B286: 43199 | C286: Kriger Campus | D286: Ed-Tech | E286: Mobile-Based Education Network | F286: Delhi | G286: N/A | H286: Seed / Angel Funding | I286: 46140 | J286: nan | K286: {=_xlfn.IFS(I286<1000000,"Bin1",AND(I286>=1000000,I286<=10000000),"Bin2",I286>10000000,"Bin3")} -> Bin1 | L286: =YEAR(B286) -> 2018 | M286: =_xlfn.XLOOKUP(C286,'LookUp Table'!$A$1:$A$3031,'LookUp Table'!$B$1:$B$3031,"Not Found",0) -> Delhi | N286: =IFERROR(VLOOKUP(G286,$W$1:$X$6025,2,FALSE),"Ignore") -> Seed / Angel Funding | O286: =_xlfn.XLOOKUP(N286,'Com LookUp+Pivot'!$A$1:$A$49,'Com LookUp+Pivot'!$B$1:$B$49,"Not Found",0) -> Angel | W286: N/A | X286: Seed / Angel Funding
A287: 292 | B287: 43200 | C287: Loanzen | D287: Finance | E287: Digital Lending Platform In Logistics | F287: Bengaluru | G287: Kae Capital Management | H287: Seed / Angel Funding | I287: 0 | J287: nan | K287: {=_xlfn.IFS(I287<1000000,"Bin1",AND(I287>=1000000,I287<=10000000),"Bin2",I287>10000000,"Bin3")} -> Bin1 | L287: =YEAR(B287) -> 2018 | M287: =_xlfn.XLOOKUP(C287,'LookUp Table'!$A$1:$A$3031,'LookUp Table'!$B$1:$B$3031,"Not Found",0) -> Bengaluru | N287: =IFERROR(VLOOKUP(G287,$W$1:$X$6025,2,FALSE),"Ignore") -> Seed / Angel Funding | O287: =_xlfn.XLOOKUP(N287,'Com LookUp+Pivot'!$A$1:$A$49,'Com LookUp+Pivot'!$B$1:$B$49,"Not Found",0) -> Angel | W287: Kae Capital Management | X287: Seed / Angel Funding
A288: 293 | B288: 43200 | C288: TravelTriangle | D288: Consumer Internet | E288: Online Travel Marketplace | F288: Gurugram | G288: Fundamentum, SAIF Partners, Bessemer Venture Partners, RB investments & Others | H288: Private Equity | I288: 12000000 | J288: nan | K288: {=_xlfn.IFS(I288<1000000,"Bin1",AND(I288>=1000000,I288<=10000000),"Bin2",I288>10000000,"Bin3")} -> Bin3 | L288: =YEAR(B288) -> 2018 | M288: =_xlfn.XLOOKUP(C288,'LookUp Table'!$A$1:$A$3031,'LookUp Table'!$B$1:$B$3031,"Not Found",0) -> Gurugram | N288: =IFERROR(VLOOKUP(G288,$W$1:$X$6025,2,FALSE),"Ignore") -> Private Equity | O288: =_xlfn.XLOOKUP(N288,'Com LookUp+Pivot'!$A$1:$A$49,'Com LookUp+Pivot'!$B$1:$B$49,"Not Found",0) -> PE | W288: Fundamentum, SAIF Partners, Bessemer Venture Partners, RB investments & Others | X288: Private Equity
A289: 294 | B289: 43202 | C289: Letsmd | D289: Healthcare | E289: Platform To Discover Healthcare Financing Options | F289: Delhi | G289: SRI Capital, Waterbridge Ventures and ThinKuvate | H289: Seed / Angel Funding | I289: 1000000 | J289: nan | K289: {=_xlfn.IFS(I289<1000000,"Bin1",AND(I289>=1000000,I289<=10000000),"Bin2",I289>10000000,"Bin3")} -> Bin2 | L289: =YEAR(B289) -> 2018 | M289: =_xlfn.XLOOKUP(C289,'LookUp Table'!$A$1:$A$3031,'LookUp Table'!$B$1:$B$3031,"Not Found",0) -> Delhi | N289: =IFERROR(VLOOKUP(G289,$W$1:$X$6025,2,FALSE),"Ignore") -> Seed / Angel Funding | O289: =_xlfn.XLOOKUP(N289,'Com LookUp+Pivot'!$A$1:$A$49,'Com LookUp+Pivot'!$B$1:$B$49,"Not Found",0) -> Angel | W289: SRI Capital, Waterbridge Ventures and ThinKuvate | X289: Seed / Angel Funding
A290: 295 | B290: 43202 | C290: AyeFinance | D290: Finance | E290: Online Lending Platform | F290: Gurugram | G290: BlueOrchard Finance Ltd, Hinduja Leyland Finance and IntelleGrow | H290: Debt Funding | I290: 46,000,00 | J290: nan | K290: {=_xlfn.IFS(I290<1000000,"Bin1",AND(I290>=1000000,I290<=10000000),"Bin2",I290>10000000,"Bin3")} -> Bin3 | L290: =YEAR(B290) -> 2018 | M290: =_xlfn.XLOOKUP(C290,'LookUp Table'!$A$1:$A$3031,'LookUp Table'!$B$1:$B$3031,"Not Found",0) -> Gurugram | N290: =IFERROR(VLOOKUP(G290,$W$1:$X$6025,2,FALSE),"Ignore") -> Debt Funding | O290: =_xlfn.XLOOKUP(N290,'Com LookUp+Pivot'!$A$1:$A$49,'Com LookUp+Pivot'!$B$1:$B$49,"Not Found",0) -> Other | W290: BlueOrchard Finance Ltd, Hinduja Leyland Finance and IntelleGrow | X290: Debt Funding
A291: 296 | B291: 43203 | C291: mintifi | D291: Finance | E291: Online Lending Platform | F291: Mumbai | G291: Lok Capital | H291: Seed / Angel Funding | I291: 2000000 | J291: nan | K291: {=_xlfn.IFS(I291<1000000,"Bin1",AND(I291>=1000000,I291<=10000000),"Bin2",I291>10000000,"Bin3")} -> Bin2 | L291: =YEAR(B291) -> 2018 | M291: =_xlfn.XLOOKUP(C291,'LookUp Table'!$A$1:$A$3031,'LookUp Table'!$B$1:$B$3031,"Not Found",0) -> Mumbai | N291: =IFERROR(VLOOKUP(G291,$W$1:$X$6025,2,FALSE),"Ignore") -> Seed / Angel Funding | O291: =_xlfn.XLOOKUP(N291,'Com LookUp+Pivot'!$A$1:$A$49,'Com LookUp+Pivot'!$B$1:$B$49,"Not Found",0) -> Angel | W291: Lok Capital | X291: Seed / Angel Funding
A292: 297 | B292: 43206 | C292: icanstay | D292: Consumer Internet | E292: Online Platform For Luxury Hotel Stay For Business Travelers | F292: Delhi | G292: Mr. Manoj Prasad | H292: Seed / Angel Funding | I292: 500000 | J292: nan | K292: {=_xlfn.IFS(I292<1000000,"Bin1",AND(I292>=1000000,I292<=10000000),"Bin2",I292>10000000,"Bin3")} -> Bin1 | L292: =YEAR(B292) -> 2018 | M292: =_xlfn.XLOOKUP(C292,'LookUp Table'!$A$1:$A$3031,'LookUp Table'!$B$1:$B$3031,"Not Found",0) -> Delhi | N292: =IFERROR(VLOOKUP(G292,$W$1:$X$6025,2,FALSE),"Ignore") -> Seed / Angel Funding | O292: =_xlfn.XLOOKUP(N292,'Com LookUp+Pivot'!$A$1:$A$49,'Com LookUp+Pivot'!$B$1:$B$49,"Not Found",0) -> Angel | W292: Mr. Manoj Prasad | X292: Seed / Angel Funding
A293: 298 | B293: 43206 | C293: Pregbuddy | D293: Healthcare | E293: Connected Care App For Pregnant Women | F293: Bengaluru | G293: Rajan Anandan, Madhusudhan Kannan, Jayant Kadambi, Puneet Gupta and Pradeep K Jaisingh | H293: Seed / Angel Funding | I293: 0 | J293: nan | K293: {=_xlfn.IFS(I293<1000000,"Bin1",AND(I293>=1000000,I293<=10000000),"Bin2",I293>10000000,"Bin3")} -> Bin1 | L293: =YEAR(B293) -> 2018 | M293: =_xlfn.XLOOKUP(C293,'LookUp Table'!$A$1:$A$3031,'LookUp Table'!$B$1:$B$3031,"Not Found",0) -> Bengaluru | N293: =IFERROR(VLOOKUP(G293,$W$1:$X$6025,2,FALSE),"Ignore") -> Seed / Angel Funding | O293: =_xlfn.XLOOKUP(N293,'Com LookUp+Pivot'!$A$1:$A$49,'Com LookUp+Pivot'!$B$1:$B$49,"Not Found",0) -> Angel | W293: Rajan Anandan, Madhusudhan Kannan, Jayant Kadambi, Puneet Gupta and Pradeep K Jaisingh | X293: Seed / Angel Funding
A294: 299 | B294: 43208 | C294: Coverfox | D294: Consumer Internet | E294: Online Insurance Aggregator | F294: Mumbai | G294: International Finance Corporation, Transamerica and others. | H294: Private Equity | I294: 22000000 | J294: nan | K294: {=_xlfn.IFS(I294<1000000,"Bin1",AND(I294>=1000000,I294<=10000000),"Bin2",I294>10000000,"Bin3")} -> Bin3 | L294: =YEAR(B294) -> 2018 | M294: =_xlfn.XLOOKUP(C294,'LookUp Table'!$A$1:$A$3031,'LookUp Table'!$B$1:$B$3031,"Not Found",0) -> Mumbai | N294: =IFERROR(VLOOKUP(G294,$W$1:$X$6025,2,FALSE),"Ignore") -> Private Equity | O294: =_xlfn.XLOOKUP(N294,'Com LookUp+Pivot'!$A$1:$A$49,'Com LookUp+Pivot'!$B$1:$B$49,"Not Found",0) -> PE | W294: International Finance Corporation, Transamerica and others. | X294: Private Equity
A295: 300 | B295: 43209 | C295: Lenskart | D295: Consumer Internet | E295: Online Eyewear Retailer | F295: Faridabad | G295: TR Capital | H295: Private Equity | I295: 0 | J295: nan | K295: {=_xlfn.IFS(I295<1000000,"Bin1",AND(I295>=1000000,I295<=10000000),"Bin2",I295>10000000,"Bin3")} -> Bin1 | L295: =YEAR(B295) -> 2018 | M295: =_xlfn.XLOOKUP(C295,'LookUp Table'!$A$1:$A$3031,'LookUp Table'!$B$1:$B$3031,"Not Found",0) -> Faridabad | N295: =IFERROR(VLOOKUP(G295,$W$1:$X$6025,2,FALSE),"Ignore") -> Private Equity | O295: =_xlfn.XLOOKUP(N295,'Com LookUp+Pivot'!$A$1:$A$49,'Com LookUp+Pivot'!$B$1:$B$49,"Not Found",0) -> PE | W295: TR Capital | X295: Private Equity
A296: 301 | B296: 43209 | C296: mamaearth | D296: Healthcare | E296: Online Baby care Products | F296: Gurugram | G296: Shilpa Shetty Kundra | H296: Private Equity | I296: 0 | J296: nan | K296: {=_xlfn.IFS(I296<1000000,"Bin1",AND(I296>=1000000,I296<=10000000),"Bin2",I296>10000000,"Bin3")} -> Bin1 | L296: =YEAR(B296) -> 2018 | M296: =_xlfn.XLOOKUP(C296,'LookUp Table'!$A$1:$A$3031,'LookUp Table'!$B$1:$B$3031,"Not Found",0) -> Bengaluru | N296: =IFERROR(VLOOKUP(G296,$W$1:$X$6025,2,FALSE),"Ignore") -> Private Equity | O296: =_xlfn.XLOOKUP(N296,'Com LookUp+Pivot'!$A$1:$A$49,'Com LookUp+Pivot'!$B$1:$B$49,"Not Found",0) -> PE | W296: Shilpa Shetty Kundra | X296: Private Equity
A297: 302 | B297: 43209 | C297: Fyle Technologies | D297: Technology | E297: AI Based Expense Management Platform | F297: Bengaluru | G297: Pravega Ventures and Beenext | H297: Seed / Angel Funding | I297: 11,000,00 | J297: nan | K297: {=_xlfn.IFS(I297<1000000,"Bin1",AND(I297>=1000000,I297<=10000000),"Bin2",I297>10000000,"Bin3")} -> Bin3 | L297: =YEAR(B297) -> 2018 | M297: =_xlfn.XLOOKUP(C297,'LookUp Table'!$A$1:$A$3031,'LookUp Table'!$B$1:$B$3031,"Not Found",0) -> Bengaluru | N297: =IFERROR(VLOOKUP(G297,$W$1:$X$6025,2,FALSE),"Ignore") -> Seed / Angel Funding | O297: =_xlfn.XLOOKUP(N297,'Com LookUp+Pivot'!$A$1:$A$49,'Com LookUp+Pivot'!$B$1:$B$49,"Not Found",0) -> Angel | W297: Pravega Ventures and Beenext | X297: Seed / Angel Funding
A298: 303 | B298: 43209 | C298: True Balance | D298: Technology | E298: Mobile Balance Checking App | F298: Gurugram | G298: Line Ventures Corporation, Line Corp, Naver, Shinhan Bank and TS Investment | H298: Private Equity | I298: 23000000 | J298: nan | K298: {=_xlfn.IFS(I298<1000000,"Bin1",AND(I298>=1000000,I298<=10000000),"Bin2",I298>10000000,"Bin3")} -> Bin3 | L298: =YEAR(B298) -> 2018 | M298: =_xlfn.XLOOKUP(C298,'LookUp Table'!$A$1:$A$3031,'LookUp Table'!$B$1:$B$3031,"Not Found",0) -> Gurugram | N298: =IFERROR(VLOOKUP(G298,$W$1:$X$6025,2,FALSE),"Ignore") -> Private Equity | O298: =_xlfn.XLOOKUP(N298,'Com LookUp+Pivot'!$A$1:$A$49,'Com LookUp+Pivot'!$B$1:$B$49,"Not Found",0) -> PE | W298: Line Ventures Corporation, Line Corp, Naver, Shinhan Bank and TS Investment | X298: Private Equity
A299: 304 | B299: 43212 | C299: Visit | D299: Healthcare | E299: AI Driven Health tech Platform | F299: Delhi | G299: Biz Stone, Kunal Bahl, Rohit Bansal, Alagu Periyannan and Karthee Madasamy | H299: Private Equity | I299: 0 | J299: nan | K299: {=_xlfn.IFS(I299<1000000,"Bin1",AND(I299>=1000000,I299<=10000000),"Bin2",I299>10000000,"Bin3")} -> Bin1 | L299: =YEAR(B299) -> 2018 | M299: =_xlfn.XLOOKUP(C299,'LookUp Table'!$A$1:$A$3031,'LookUp Table'!$B$1:$B$3031,"Not Found",0) -> Delhi | N299: =IFERROR(VLOOKUP(G299,$W$1:$X$6025,2,FALSE),"Ignore") -> Private Equity | O299: =_xlfn.XLOOKUP(N299,'Com LookUp+Pivot'!$A$1:$A$49,'Com LookUp+Pivot'!$B$1:$B$49,"Not Found",0) -> PE | W299: Biz Stone, Kunal Bahl, Rohit Bansal, Alagu Periyannan and Karthee Madasamy | X299: Private Equity
A300: 305 | B300: 43212 | C300: Doxper | D300: Healthcare | E300: Digitized Health-Tech Solutions For Practitioners | F300: Mumbai | G300: Vidal Healthcare | H300: Seed / Angel Funding | I300: 1900000 | J300: nan | K300: {=_xlfn.IFS(I300<1000000,"Bin1",AND(I300>=1000000,I300<=10000000),"Bin2",I300>10000000,"Bin3")} -> Bin2 | L300: =YEAR(B300) -> 2018 | M300: =_xlfn.XLOOKUP(C300,'LookUp Table'!$A$1:$A$3031,'LookUp Table'!$B$1:$B$3031,"Not Found",0) -> Mumbai | N300: =IFERROR(VLOOKUP(G300,$W$1:$X$6025,2,FALSE),"Ignore") -> Seed / Angel Funding | O300: =_xlfn.XLOOKUP(N300,'Com LookUp+Pivot'!$A$1:$A$49,'Com LookUp+Pivot'!$B$1:$B$49,"Not Found",0) -> Angel | W300: Vidal Healthcare | X300: Seed / Angel Funding
A301: 306 | B301: 43212 | C301: Nykaa | D301: Consumer Internet | E301: Beauty e-tailer | F301: Mumbai | G301: Sunil Munjal, Harsh Mariwala, Dalip Pathak and Others | H301: Private Equity | I301: 11000000 | J301: nan | K301: {=_xlfn.IFS(I301<1000000,"Bin1",AND(I301>=1000000,I301<=10000000),"Bin2",I301>10000000,"Bin3")} -> Bin3 | L301: =YEAR(B301) -> 2018 | M301: =_xlfn.XLOOKUP(C301,'LookUp Table'!$A$1:$A$3031,'LookUp Table'!$B$1:$B$3031,"Not Found",0) -> Mumbai | N301: =IFERROR(VLOOKUP(G301,$W$1:$X$6025,2,FALSE),"Ignore") -> Private Equity | O301: =_xlfn.XLOOKUP(N301,'Com LookUp+Pivot'!$A$1:$A$49,'Com LookUp+Pivot'!$B$1:$B$49,"Not Found",0) -> PE | W301: Sunil Munjal, Harsh Mariwala, Dalip Pathak and Others | X301: Private Equity
A302: 307 | B302: 43213 | C302: Mihuru | D302: Finance | E302: Online Platform Providing Micro Loans For Air Travel | F302: Mumbai | G302: N/A | H302: Seed / Angel Funding | I302: 150000 | J302: nan | K302: {=_xlfn.IFS(I302<1000000,"Bin1",AND(I302>=1000000,I302<=10000000),"Bin2",I302>10000000,"Bin3")} -> Bin1 | L302: =YEAR(B302) -> 2018 | M302: =_xlfn.XLOOKUP(C302,'LookUp Table'!$A$1:$A$3031,'LookUp Table'!$B$1:$B$3031,"Not Found",0) -> Mumbai | N302: =IFERROR(VLOOKUP(G302,$W$1:$X$6025,2,FALSE),"Ignore") -> Seed / Angel Funding | O302: =_xlfn.XLOOKUP(N302,'Com LookUp+Pivot'!$A$1:$A$49,'Com LookUp+Pivot'!$B$1:$B$49,"Not Found",0) -> Angel | W302: N/A | X302: Seed / Angel Funding
A303: 308 | B303: 43213 | C303: Capital Float | D303: Finance | E303: Online Lending Platform | F303: Bengaluru | G303: Amazon | H303: Private Equity | I303: 22000000 | J303: nan | K303: {=_xlfn.IFS(I303<1000000,"Bin1",AND(I303>=1000000,I303<=10000000),"Bin2",I303>10000000,"Bin3")} -> Bin3 | L303: =YEAR(B303) -> 2018 | M303: =_xlfn.XLOOKUP(C303,'LookUp Table'!$A$1:$A$3031,'LookUp Table'!$B$1:$B$3031,"Not Found",0) -> Bengaluru | N303: =IFERROR(VLOOKUP(G303,$W$1:$X$6025,2,FALSE),"Ignore") -> Private Equity | O303: =_xlfn.XLOOKUP(N303,'Com LookUp+Pivot'!$A$1:$A$49,'Com LookUp+Pivot'!$B$1:$B$49,"Not Found",0) -> PE | W303: Amazon | X303: Private Equity
A304: 309 | B304: 43215 | C304: Trip shelf | D304: Consumer Internet | E304: Online Travel Marketplace | F304: Delhi | G304: GEMS Advisory, Alok Mittal and Sachin Bhatia | H304: Seed / Angel Funding | I304: 246000 | J304: nan | K304: {=_xlfn.IFS(I304<1000000,"Bin1",AND(I304>=1000000,I304<=10000000),"Bin2",I304>10000000,"Bin3")} -> Bin1 | L304: =YEAR(B304) -> 2018 | M304: =_xlfn.XLOOKUP(C304,'LookUp Table'!$A$1:$A$3031,'LookUp Table'!$B$1:$B$3031,"Not Found",0) -> Delhi | N304: =IFERROR(VLOOKUP(G304,$W$1:$X$6025,2,FALSE),"Ignore") -> Seed / Angel Funding | O304: =_xlfn.XLOOKUP(N304,'Com LookUp+Pivot'!$A$1:$A$49,'Com LookUp+Pivot'!$B$1:$B$49,"Not Found",0) -> Angel | W304: GEMS Advisory, Alok Mittal and Sachin Bhatia | X304: Seed / Angel Funding
A305: 310 | B305: 43216 | C305: POPxo | D305: Technology | E305: Women Focussed Digital Media Platform | F305: Delhi | G305: Neoplux, OPPO, IDG Ventures India, Kalaari Capital, GREE Ventures and Summit Media | H305: Private Equity | I305: 5500000 | J305: nan | K305: {=_xlfn.IFS(I305<1000000,"Bin1",AND(I305>=1000000,I305<=10000000),"Bin2",I305>10000000,"Bin3")} -> Bin2 | L305: =YEAR(B305) -> 2018 | M305: =_xlfn.XLOOKUP(C305,'LookUp Table'!$A$1:$A$3031,'LookUp Table'!$B$1:$B$3031,"Not Found",0) -> Delhi | N305: =IFERROR(VLOOKUP(G305,$W$1:$X$6025,2,FALSE),"Ignore") -> Private Equity | O305: =_xlfn.XLOOKUP(N305,'Com LookUp+Pivot'!$A$1:$A$49,'Com LookUp+Pivot'!$B$1:$B$49,"Not Found",0) -> PE | W305: Neoplux, OPPO, IDG Ventures India, Kalaari Capital, GREE Ventures and Summit Media | X305: Private Equity
A306: 311 | B306: 43216 | C306: RailYatri | D306: Consumer Internet | E306: Online Travel Ticketing Platform | F306: Noida | G306: Omidyar Network, Nandan Nilekani, Blume Ventures, Helion Venture Partners | H306: Private Equity | I306: 0 | J306: nan | K306: {=_xlfn.IFS(I306<1000000,"Bin1",AND(I306>=1000000,I306<=10000000),"Bin2",I306>10000000,"Bin3")} -> Bin1 | L306: =YEAR(B306) -> 2018 | M306: =_xlfn.XLOOKUP(C306,'LookUp Table'!$A$1:$A$3031,'LookUp Table'!$B$1:$B$3031,"Not Found",0) -> Noida | N306: =IFERROR(VLOOKUP(G306,$W$1:$X$6025,2,FALSE),"Ignore") -> Private Equity | O306: =_xlfn.XLOOKUP(N306,'Com LookUp+Pivot'!$A$1:$A$49,'Com LookUp+Pivot'!$B$1:$B$49,"Not Found",0) -> PE | W306: Omidyar Network, Nandan Nilekani, Blume Ventures, Helion Venture Partners | X306: Private Equity
A307: 312 | B307: 43217 | C307: 1mg | D307: Consumer Internet | E307: Online Pharmacy Store | F307: Gurugram | G307: Sequoia Capital, Maverick Capital Ltd and HBM Healthcare Investments Ltd | H307: Private Equity | I307: 10000000 | J307: nan | K307: {=_xlfn.IFS(I307<1000000,"Bin1",AND(I307>=1000000,I307<=10000000),"Bin2",I307>10000000,"Bin3")} -> Bin2 | L307: =YEAR(B307) -> 2018 | M307: =_xlfn.XLOOKUP(C307,'LookUp Table'!$A$1:$A$3031,'LookUp Table'!$B$1:$B$3031,"Not Found",0) -> Gurugram | N307: =IFERROR(VLOOKUP(G307,$W$1:$X$6025,2,FALSE),"Ignore") -> Private Equity | O307: =_xlfn.XLOOKUP(N307,'Com LookUp+Pivot'!$A$1:$A$49,'Com LookUp+Pivot'!$B$1:$B$49,"Not Found",0) -> PE | W307: Sequoia Capital, Maverick Capital Ltd and HBM Healthcare Investments Ltd | X307: Private Equity
A308: 313 | B308: 43219 | C308: Rubique | D308: Consumer Internet | E308: Online Lending MarketPlace | F308: Mumbai | G308: Emery Capital, Blacksoil and Kalaari Capital | H308: Private Equity | I308: 0 | J308: nan | K308: {=_xlfn.IFS(I308<1000000,"Bin1",AND(I308>=1000000,I308<=10000000),"Bin2",I308>10000000,"Bin3")} -> Bin1 | L308: =YEAR(B308) -> 2018 | M308: =_xlfn.XLOOKUP(C308,'LookUp Table'!$A$1:$A$3031,'LookUp Table'!$B$1:$B$3031,"Not Found",0) -> Mumbai | N308: =IFERROR(VLOOKUP(G308,$W$1:$X$6025,2,FALSE),"Ignore") -> Private Equity | O308: =_xlfn.XLOOKUP(N308,'Com LookUp+Pivot'!$A$1:$A$49,'Com LookUp+Pivot'!$B$1:$B$49,"Not Found",0) -> PE | W308: Emery Capital, Blacksoil and Kalaari Capital | X308: Private Equity
A309: 314 | B309: 43220 | C309: Samco | D309: Consumer Internet | E309: Online Stock Broker | F309: Mumbai | G309: Bay Capital Investments and Others | H309: Private Equity | I309: 7500000 | J309: nan | K309: {=_xlfn.IFS(I309<1000000,"Bin1",AND(I309>=1000000,I309<=10000000),"Bin2",I309>10000000,"Bin3")} -> Bin2 | L309: =YEAR(B309) -> 2018 | M309: =_xlfn.XLOOKUP(C309,'LookUp Table'!$A$1:$A$3031,'LookUp Table'!$B$1:$B$3031,"Not Found",0) -> Mumbai | N309: =IFERROR(VLOOKUP(G309,$W$1:$X$6025,2,FALSE),"Ignore") -> Private Equity | O309: =_xlfn.XLOOKUP(N309,'Com LookUp+Pivot'!$A$1:$A$49,'Com LookUp+Pivot'!$B$1:$B$49,"Not Found",0) -> PE | W309: Bay Capital Investments and Others | X309: Private Equity
... A2100: 2108 | B2100: 42399 | C2100: DesignBids | D2100: Consumer Internet | E2100: Interior Design Marketplace | F2100: New Delhi | G2100: Indian Angel Network | H2100: Seed Funding | I2100: 0 | J2100: nan | K2100: {=_xlfn.IFS(I2100<1000000,"Bin1",AND(I2100>=1000000,I2100<=10000000),"Bin2",I2100>10000000,"Bin3")} -> Bin1 | L2100: =YEAR(B2100) -> 2016 | M2100: =_xlfn.XLOOKUP(C2100,'LookUp Table'!$A$1:$A$3031,'LookUp Table'!$B$1:$B$3031,"Not Found",0) -> New Delhi | N2100: =IFERROR(VLOOKUP(G2100,$W$1:$X$6025,2,FALSE),"Ignore") -> Seed Funding | O2100: =_xlfn.XLOOKUP(N2100,'Com LookUp+Pivot'!$A$1:$A$49,'Com LookUp+Pivot'!$B$1:$B$49,"Not Found",0) -> Angel | W2100: Indian Angel Network | X2100: Seed Funding
A2101: 2109 | B2101: 42339 | C2101: CollegeDekho | D2101: Online Education Information platform | E2101: nan | F2101: Jaipur | G2101: GirnarSoft | H2101: Seed Funding | I2101: 1000000 | K2101: {=_xlfn.IFS(I2101<1000000,"Bin1",AND(I2101>=1000000,I2101<=10000000),"Bin2",I2101>10000000,"Bin3")} -> Bin2 | L2101: =YEAR(B2101) -> 2015 | M2101: =_xlfn.XLOOKUP(C2101,'LookUp Table'!$A$1:$A$3031,'LookUp Table'!$B$1:$B$3031,"Not Found",0) -> Gurugram | N2101: =IFERROR(VLOOKUP(G2101,$W$1:$X$6025,2,FALSE),"Ignore") -> Private Equity | O2101: =_xlfn.XLOOKUP(N2101,'Com LookUp+Pivot'!$A$1:$A$49,'Com LookUp+Pivot'!$B$1:$B$49,"Not Found",0) -> PE | W2101: GirnarSoft | X2101: Seed Funding
A2102: 2110 | B2102: 42339 | C2102: Black White Orange Brands | D2102: Brand Licensing Startup | E2102: nan | F2102: Mumbai | G2102: YouWeCan Ventures | H2102: Seed Funding | I2102: 0 | K2102: {=_xlfn.IFS(I2102<1000000,"Bin1",AND(I2102>=1000000,I2102<=10000000),"Bin2",I2102>10000000,"Bin3")} -> Bin1 | L2102: =YEAR(B2102) -> 2015 | M2102: =_xlfn.XLOOKUP(C2102,'LookUp Table'!$A$1:$A$3031,'LookUp Table'!$B$1:$B$3031,"Not Found",0) -> Mumbai | N2102: =IFERROR(VLOOKUP(G2102,$W$1:$X$6025,2,FALSE),"Ignore") -> Seed Funding | O2102: =_xlfn.XLOOKUP(N2102,'Com LookUp+Pivot'!$A$1:$A$49,'Com LookUp+Pivot'!$B$1:$B$49,"Not Found",0) -> Angel | W2102: YouWeCan Ventures | X2102: Seed Funding
A2103: 2111 | B2103: 42339 | C2103: Biteclub | D2103: Gourmet Food Discovery & Delivery platform | E2103: nan | F2103: Gurgaon | G2103: growX ventures | H2103: Private Equity | I2103: 0 | J2103: Pre-Series A | K2103: {=_xlfn.IFS(I2103<1000000,"Bin1",AND(I2103>=1000000,I2103<=10000000),"Bin2",I2103>10000000,"Bin3")} -> Bin1 | L2103: =YEAR(B2103) -> 2015 | M2103: =_xlfn.XLOOKUP(C2103,'LookUp Table'!$A$1:$A$3031,'LookUp Table'!$B$1:$B$3031,"Not Found",0) -> Gurgaon | N2103: =IFERROR(VLOOKUP(G2103,$W$1:$X$6025,2,FALSE),"Ignore") -> Private Equity | O2103: =_xlfn.XLOOKUP(N2103,'Com LookUp+Pivot'!$A$1:$A$49,'Com LookUp+Pivot'!$B$1:$B$49,"Not Found",0) -> PE | W2103: growX ventures | X2103: Private Equity
A2104: 2112 | B2104: 42339 | C2104: Patel Logistics | D2104: Transportation & Logistics Platform | E2104: nan | F2104: Mumbai | G2104: Frontline Strategy | H2104: Private Equity | I2104: 5600000 | J2104: N/A | K2104: {=_xlfn.IFS(I2104<1000000,"Bin1",AND(I2104>=1000000,I2104<=10000000),"Bin2",I2104>10000000,"Bin3")} -> Bin2 | L2104: =YEAR(B2104) -> 2015 | M2104: =_xlfn.XLOOKUP(C2104,'LookUp Table'!$A$1:$A$3031,'LookUp Table'!$B$1:$B$3031,"Not Found",0) -> Mumbai | N2104: =IFERROR(VLOOKUP(G2104,$W$1:$X$6025,2,FALSE),"Ignore") -> Private Equity | O2104: =_xlfn.XLOOKUP(N2104,'Com LookUp+Pivot'!$A$1:$A$49,'Com LookUp+Pivot'!$B$1:$B$49,"Not Found",0) -> PE | W2104: Frontline Strategy | X2104: Private Equity
A2105: 2113 | B2105: 42339 | C2105: Wigzo | D2105: Enterprise Marketing Automation platform | E2105: nan | F2105: New Delhi | G2105: Aarin Capital Partners, TV Mohandas Pai | H2105: Seed Funding | I2105: 500000 | J2105: Pre-Series A | K2105: {=_xlfn.IFS(I2105<1000000,"Bin1",AND(I2105>=1000000,I2105<=10000000),"Bin2",I2105>10000000,"Bin3")} -> Bin1 | L2105: =YEAR(B2105) -> 2015 | M2105: =_xlfn.XLOOKUP(C2105,'LookUp Table'!$A$1:$A$3031,'LookUp Table'!$B$1:$B$3031,"Not Found",0) -> New Delhi | N2105: =IFERROR(VLOOKUP(G2105,$W$1:$X$6025,2,FALSE),"Ignore") -> Seed Funding | O2105: =_xlfn.XLOOKUP(N2105,'Com LookUp+Pivot'!$A$1:$A$49,'Com LookUp+Pivot'!$B$1:$B$49,"Not Found",0) -> Angel | W2105: Aarin Capital Partners, TV Mohandas Pai | X2105: Seed Funding
A2106: 2114 | B2106: 42339 | C2106: Zapluk | D2106: Health, Wellness & Beauty Services App | E2106: nan | F2106: Hyderabad | G2106: N/A | H2106: Seed Funding | I2106: 0 | K2106: {=_xlfn.IFS(I2106<1000000,"Bin1",AND(I2106>=1000000,I2106<=10000000),"Bin2",I2106>10000000,"Bin3")} -> Bin1 | L2106: =YEAR(B2106) -> 2015 | M2106: =_xlfn.XLOOKUP(C2106,'LookUp Table'!$A$1:$A$3031,'LookUp Table'!$B$1:$B$3031,"Not Found",0) -> Hyderabad | N2106: =IFERROR(VLOOKUP(G2106,$W$1:$X$6025,2,FALSE),"Ignore") -> Seed / Angel Funding | O2106: =_xlfn.XLOOKUP(N2106,'Com LookUp+Pivot'!$A$1:$A$49,'Com LookUp+Pivot'!$B$1:$B$49,"Not Found",0) -> Angel | W2106: N/A | X2106: Seed Funding
A2107: 2115 | B2107: 42339 | C2107: Godof Hospitals | D2107: Digital Healthcare | E2107: nan | F2107: New Delhi | G2107: Pankaj Gupta | H2107: Seed Funding | I2107: 2000000 | K2107: {=_xlfn.IFS(I2107<1000000,"Bin1",AND(I2107>=1000000,I2107<=10000000),"Bin2",I2107>10000000,"Bin3")} -> Bin2 | L2107: =YEAR(B2107) -> 2015 | M2107: =_xlfn.XLOOKUP(C2107,'LookUp Table'!$A$1:$A$3031,'LookUp Table'!$B$1:$B$3031,"Not Found",0) -> New Delhi | N2107: =IFERROR(VLOOKUP(G2107,$W$1:$X$6025,2,FALSE),"Ignore") -> Seed Funding | O2107: =_xlfn.XLOOKUP(N2107,'Com LookUp+Pivot'!$A$1:$A$49,'Com LookUp+Pivot'!$B$1:$B$49,"Not Found",0) -> Angel | W2107: Pankaj Gupta | X2107: Seed Funding
A2108: 2116 | B2108: 42340 | C2108: RoomsTonite | D2108: Last Minute Hotel Booking App | E2108: nan | F2108: Bangalore | G2108: Lashit Sanghvi, Nikhil Vora, Venkat Vardhan,Mohammed Bin Abdul Rehman Al Khalifa,\\xc2\\xa0 Ralph Berezan, Vissal Mathew,\\xc2\\xa0 Balamurali Krishna | H2108: Seed Funding | I2108: 1500000 | K2108: {=_xlfn.IFS(I2108<1000000,"Bin1",AND(I2108>=1000000,I2108<=10000000),"Bin2",I2108>10000000,"Bin3")} -> Bin2 | L2108: =YEAR(B2108) -> 2015 | M2108: =_xlfn.XLOOKUP(C2108,'LookUp Table'!$A$1:$A$3031,'LookUp Table'!$B$1:$B$3031,"Not Found",0) -> Bangalore | N2108: =IFERROR(VLOOKUP(G2108,$W$1:$X$6025,2,FALSE),"Ignore") -> Seed Funding | O2108: =_xlfn.XLOOKUP(N2108,'Com LookUp+Pivot'!$A$1:$A$49,'Com LookUp+Pivot'!$B$1:$B$49,"Not Found",0) -> Angel | W2108: Lashit Sanghvi, Nikhil Vora, Venkat Vardhan,Mohammed Bin Abdul Rehman Al Khalifa,\\xc2\\xa0 Ralph Berezan, Vissal Mathew,\\xc2\\xa0 Balamurali Krishna | X2108: Seed Funding
A2109: 2117 | B2109: 42340 | C2109: Kaaryah | D2109: Womens Fashion Wear Portal | E2109: nan | F2109: New Delhi | G2109: The Saha Fund, TV Mohandas Pai | H2109: Private Equity | I2109: 0 | J2109: Pre-Series A | K2109: {=_xlfn.IFS(I2109<1000000,"Bin1",AND(I2109>=1000000,I2109<=10000000),"Bin2",I2109>10000000,"Bin3")} -> Bin1 | L2109: =YEAR(B2109) -> 2015 | M2109: =_xlfn.XLOOKUP(C2109,'LookUp Table'!$A$1:$A$3031,'LookUp Table'!$B$1:$B$3031,"Not Found",0) -> New Delhi | N2109: =IFERROR(VLOOKUP(G2109,$W$1:$X$6025,2,FALSE),"Ignore") -> Private Equity | O2109: =_xlfn.XLOOKUP(N2109,'Com LookUp+Pivot'!$A$1:$A$49,'Com LookUp+Pivot'!$B$1:$B$49,"Not Found",0) -> PE | W2109: The Saha Fund, TV Mohandas Pai | X2109: Private Equity
...

Sheet LookUp Table
A1: Startup Name | B1: City Location
A2: BYJU’S | B2: Bengaluru
A3: Shuttl | B3: Gurgaon
A4: Mamaearth | B4: Bengaluru
A5: https://www.wealthbucket.in/ | B5: New Delhi
A6: Fashor | B6: Mumbai
A7: Pando | B7: Chennai
A8: Zomato | B8: Gurgaon
A9: Ecozen | B9: Pune
A10: CarDekho | B10: Gurgaon
A11: Dhruva Space | B11: Bengaluru
A12: Rivigo | B12: Gurgaon
... A3031: couponmachine.in | B3031: nan

Sheet Com LookUp+Pivot
A1: Investor Type | B1: Classification Investor Type
A2: Private Equity Round | B2: =IF(OR(ISNUMBER(SEARCH("seed",A2)),ISNUMBER(SEARCH("angel",A2))), "Angel", IF(OR(ISNUMBER(SEARCH("series",A2)),ISNUMBER(SEARCH("pre-series",A2))), "VC", IF(ISNUMBER(SEARCH("equity",A2)), "PE", "Other"))) -> PE
A3: Series C | B3: =IF(OR(ISNUMBER(SEARCH("seed",A3)),ISNUMBER(SEARCH("angel",A3))), "Angel", IF(OR(ISNUMBER(SEARCH("series",A3)),ISNUMBER(SEARCH("pre-series",A3))), "VC", IF(ISNUMBER(SEARCH("equity",A3)), "PE", "Other"))) -> VC
A4: Series B | B4: =IF(OR(ISNUMBER(SEARCH("seed",A4)),ISNUMBER(SEARCH("angel",A4))), "Angel", IF(OR(ISNUMBER(SEARCH("series",A4)),ISNUMBER(SEARCH("pre-series",A4))), "VC", IF(ISNUMBER(SEARCH("equity",A4)), "PE", "Other"))) -> VC
A5: Pre-series A | B5: =IF(OR(ISNUMBER(SEARCH("seed",A5)),ISNUMBER(SEARCH("angel",A5))), "Angel", IF(OR(ISNUMBER(SEARCH("series",A5)),ISNUMBER(SEARCH("pre-series",A5))), "VC", IF(ISNUMBER(SEARCH("equity",A5)), "PE", "Other"))) -> VC
A6: Seed Round | B6: =IF(OR(ISNUMBER(SEARCH("seed",A6)),ISNUMBER(SEARCH("angel",A6))), "Angel", IF(OR(ISNUMBER(SEARCH("series",A6)),ISNUMBER(SEARCH("pre-series",A6))), "VC", IF(ISNUMBER(SEARCH("equity",A6)), "PE", "Other"))) -> Angel
A7: Series A | B7: =IF(OR(ISNUMBER(SEARCH("seed",A7)),ISNUMBER(SEARCH("angel",A7))), "Angel", IF(OR(ISNUMBER(SEARCH("series",A7)),ISNUMBER(SEARCH("pre-series",A7))), "VC", IF(ISNUMBER(SEARCH("equity",A7)), "PE", "Other"))) -> VC
A8: Series D | B8: =IF(OR(ISNUMBER(SEARCH("seed",A8)),ISNUMBER(SEARCH("angel",A8))), "Angel", IF(OR(ISNUMBER(SEARCH("series",A8)),ISNUMBER(SEARCH("pre-series",A8))), "VC", IF(ISNUMBER(SEARCH("equity",A8)), "PE", "Other"))) -> VC
A9: Seed | B9: =IF(OR(ISNUMBER(SEARCH("seed",A9)),ISNUMBER(SEARCH("angel",A9))), "Angel", IF(OR(ISNUMBER(SEARCH("series",A9)),ISNUMBER(SEARCH("pre-series",A9))), "VC", IF(ISNUMBER(SEARCH("equity",A9)), "PE", "Other"))) -> Angel
A10: Series F | B10: =IF(OR(ISNUMBER(SEARCH("seed",A10)),ISNUMBER(SEARCH("angel",A10))), "Angel", IF(OR(ISNUMBER(SEARCH("series",A10)),ISNUMBER(SEARCH("pre-series",A10))), "VC", IF(ISNUMBER(SEARCH("equity",A10)), "PE", "Other"))) -> VC
A11: Series E | B11: =IF(OR(ISNUMBER(SEARCH("seed",A11)),ISNUMBER(SEARCH("angel",A11))), "Angel", IF(OR(ISNUMBER(SEARCH("series",A11)),ISNUMBER(SEARCH("pre-series",A11))), "VC", IF(ISNUMBER(SEARCH("equity",A11)), "PE", "Other"))) -> VC
A12: Series G | B12: =IF(OR(ISNUMBER(SEARCH("seed",A12)),ISNUMBER(SEARCH("angel",A12))), "Angel", IF(OR(ISNUMBER(SEARCH("series",A12)),ISNUMBER(SEARCH("pre-series",A12))), "VC", IF(ISNUMBER(SEARCH("equity",A12)), "PE", "Other"))) -> VC
A13: Series H | B13: =IF(OR(ISNUMBER(SEARCH("seed",A13)),ISNUMBER(SEARCH("angel",A13))), "Angel", IF(OR(ISNUMBER(SEARCH("series",A13)),ISNUMBER(SEARCH("pre-series",A13))), "VC", IF(ISNUMBER(SEARCH("equity",A13)), "PE", "Other"))) -> VC
... A49: Crowd funding | B49: =IF(OR(ISNUMBER(SEARCH("seed",A49)),ISNUMBER(SEARCH("angel",A49))), "Angel", IF(OR(ISNUMBER(SEARCH("series",A49)),ISNUMBER(SEARCH("pre-series",A49))), "VC", IF(ISNUMBER(SEARCH("equity",A49)), "PE", "Other"))) -> Other
